[
  {
    "instagram_handle": "@natachalight",
    "twitter_handle": null,
    "nom": "Natacha",
    "bio": "🙋🏻‍♀️ Natacha TIKTOK : natachalight (+200k de stars🫶🏻) 💌 natachalight@protonmail.com",
    "ville": "Paris",
    "abonnes_instagram": 78800,
    "abonnes_affiche": "78.8k",
    "secteur": "clinique_esthetique",
    "email_contact": "natachalight@protonmail.com",
    "tarif_estime": "300-600€",
    "statut": "à_contacter",
    "dans_cible": true,
    "source": "modash",
    "date_contact": null,
    "scraped_at": "2026-05-14T19:05:54.047Z"
  },
  {
    "instagram_handle": "@biotenaturelle",
    "twitter_handle": null,
    "nom": "Bioté Naturelle - Aline",
    "bio": "🔍 La meuf qui analyse les dessous de tes produits 🌸 Skincare et beauté 𝘷𝘳𝘢𝘪𝘮𝘦𝘯𝘵 clean 💌 contact@biotenaturelle.fr ✨ @zed.atelier & @uneviedaline",
    "ville": "Paris",
    "abonnes_instagram": 59600,
    "abonnes_affiche": "59.6k",
    "secteur": "clinique_esthetique",
    "email_contact": "contact@biotenaturelle.fr",
    "tarif_estime": "300-600€",
    "statut": "à_contacter",
    "dans_cible": true,
    "source": "modash",
    "date_contact": null,
    "scraped_at": "2026-05-14T19:05:54.047Z"
  },
  {
    "instagram_handle": "@lolatesca",
    "twitter_handle": null,
    "nom": "Lola Tesca",
    "bio": "find me in the kitchen 🍪 or doing skincare 🫧 (on an island) ✉️ lolatesca@gmail.com",
    "ville": "Paris",
    "abonnes_instagram": 31100,
    "abonnes_affiche": "31.1k",
    "secteur": "clinique_esthetique",
    "email_contact": "lolatesca@gmail.com",
    "tarif_estime": "150-300€",
    "statut": "à_contacter",
    "dans_cible": true,
    "source": "modash",
    "date_contact": null,
    "scraped_at": "2026-05-14T19:05:54.047Z"
  },
  {
    "instagram_handle": "@lesdecouvertesdestef",
    "twitter_handle": null,
    "nom": "Stéphanie 🌺 en toute simplicité 🌺 créatrice authentique",
    "bio": "✨️Mes Avis stephetsestests@gmail.com #ugc#cancersurvivor#lifestyle#perfumeaddict#beauty#skincare 50 & épanouie Stylevana INF10DESTEF/YesStyle STEPH40",
    "ville": "Paris",
    "abonnes_instagram": 20600,
    "abonnes_affiche": "20.6k",
    "secteur": "clinique_esthetique",
    "email_contact": "stephetsestests@gmail.com",
    "tarif_estime": "150-300€",
    "statut": "à_contacter",
    "dans_cible": true,
    "source": "modash",
    "date_contact": null,
    "scraped_at": "2026-05-14T19:05:54.047Z"
  },
  {
    "instagram_handle": "@diaryofascorpion",
    "twitter_handle": null,
    "nom": "Diaryofascorpion 🐻 | OCÉANE 🦂",
    "bio": "📍Strasbourg, 67 💋PARFUM | MAKEUP | SKINCARE 📩 ocevy70@hotmail.fr ▶️Tik tok : diaryofascorpion ✨Good vibes only, simplicity✨ #ᴄᴏɴᴛᴇɴᴛᴄʀᴇᴀᴛᴏʀ #beauty",
    "ville": "Strasbourg",
    "abonnes_instagram": 16500,
    "abonnes_affiche": "16.5k",
    "secteur": "clinique_esthetique",
    "email_contact": "ocevy70@hotmail.fr",
    "tarif_estime": "50-150€",
    "statut": "à_contacter",
    "dans_cible": true,
    "source": "modash",
    "date_contact": null,
    "scraped_at": "2026-05-14T19:05:54.047Z"
  },
  {
    "instagram_handle": "@jti.giulia",
    "twitter_handle": null,
    "nom": "Giulia",
    "bio": "🌟Créatrice de contenu 🔸 YesStyle influencer Mode / Beauty / Skincare 📩 giuliajti78@gmail.com 💬DM pour collaboration",
    "ville": "Paris",
    "abonnes_instagram": 15300,
    "abonnes_affiche": "15.3k",
    "secteur": "clinique_esthetique",
    "email_contact": "giuliajti78@gmail.com",
    "tarif_estime": "50-150€",
    "statut": "à_contacter",
    "dans_cible": true,
    "source": "modash",
    "date_contact": null,
    "scraped_at": "2026-05-14T19:05:54.047Z"
  },
  {
    "instagram_handle": "@leannamadeit",
    "twitter_handle": null,
    "nom": "Léanna | Premium Beauty Content Creator",
    "bio": "Makeup & Skincare | 4K video production ✨ PR/Influence : leanna@omiamanagement.com UGC : leannabelmonte.ugc@gmail.com Formatrice UGC - @richandglowy",
    "ville": "Paris",
    "abonnes_instagram": 12500,
    "abonnes_affiche": "12.5k",
    "secteur": "clinique_esthetique",
    "email_contact": "leanna@omiamanagement.com",
    "tarif_estime": "50-150€",
    "statut": "à_contacter",
    "dans_cible": true,
    "source": "modash",
    "date_contact": null,
    "scraped_at": "2026-05-14T19:05:54.047Z"
  },
  {
    "instagram_handle": "@melissa__azak",
    "twitter_handle": null,
    "nom": "Tell me Mel ⭐",
    "bio": ". Fashion Beauty & Lifestyle ✨ . Fashion designer . melissaazak@migosmedia.com . Paris📍 . 62",
    "ville": "Paris",
    "abonnes_instagram": 43500,
    "abonnes_affiche": "43.5k",
    "secteur": "estheticienne",
    "email_contact": "melissaazak@migosmedia.com",
    "tarif_estime": "150-300€",
    "statut": "à_contacter",
    "dans_cible": true,
    "source": "modash",
    "date_contact": null,
    "scraped_at": "2026-05-14T19:05:54.046Z"
  },
  {
    "instagram_handle": "@alohamaera",
    "twitter_handle": null,
    "nom": "maera",
    "bio": "paris 💌 alohamaera@hotmail.com",
    "ville": "Paris",
    "abonnes_instagram": 41600,
    "abonnes_affiche": "41.6k",
    "secteur": "estheticienne",
    "email_contact": "alohamaera@hotmail.com",
    "tarif_estime": "150-300€",
    "statut": "à_contacter",
    "dans_cible": true,
    "source": "modash",
    "date_contact": null,
    "scraped_at": "2026-05-14T19:05:54.046Z"
  },
  {
    "instagram_handle": "@parfum_cerise",
    "twitter_handle": null,
    "nom": "Cerise 🍒 vlogs & beauty",
    "bio": "💌 Cerise@agency-yuzu.com 📍 Paris • romanticizing life • culture 🌬️ Yesstyle code: PARFUM18 @papier_cerisier",
    "ville": "Paris",
    "abonnes_instagram": 39400,
    "abonnes_affiche": "39.4k",
    "secteur": "estheticienne",
    "email_contact": "cerise@agency-yuzu.com",
    "tarif_estime": "150-300€",
    "statut": "à_contacter",
    "dans_cible": true,
    "source": "modash",
    "date_contact": null,
    "scraped_at": "2026-05-14T19:05:54.046Z"
  },
  {
    "instagram_handle": "@lavieenlucie",
    "twitter_handle": null,
    "nom": "La vie en Lucie 🌞",
    "bio": "La vraie vie 🙌🏼 Bien-être, acceptation de soi & self-love 🥰 Mode midsize & beauty addict 👜 📍Paris / Issy-les-Moulineaux 💌 lavieenlucie@gmail.com",
    "ville": "Paris",
    "abonnes_instagram": 37900,
    "abonnes_affiche": "37.9k",
    "secteur": "estheticienne",
    "email_contact": "lavieenlucie@gmail.com",
    "tarif_estime": "150-300€",
    "statut": "à_contacter",
    "dans_cible": true,
    "source": "modash",
    "date_contact": null,
    "scraped_at": "2026-05-14T19:05:54.046Z"
  },
  {
    "instagram_handle": "@c_makeup_",
    "twitter_handle": null,
    "nom": "CMAKEUP BEAUTY",
    "bio": "Pro Makeup Artist 💕 📍Paris, International Bride booking : cmakeupbeauty95@gmail.com @cmakeupbridal 💍 @loveinmotions_ 🎥 Prises de rdv (invitées)👇",
    "ville": "Paris",
    "abonnes_instagram": 35600,
    "abonnes_affiche": "35.6k",
    "secteur": "estheticienne",
    "email_contact": "cmakeupbeauty95@gmail.com",
    "tarif_estime": "150-300€",
    "statut": "à_contacter",
    "dans_cible": true,
    "source": "modash",
    "date_contact": null,
    "scraped_at": "2026-05-14T19:05:54.046Z"
  },
  {
    "instagram_handle": "@amandambt",
    "twitter_handle": null,
    "nom": "Amanda",
    "bio": "📍Paris / Londres • beauty | lifestyle •Tiktok : amandambt_ (+110k) •amanda@grapperagency.com",
    "ville": "Paris",
    "abonnes_instagram": 26900,
    "abonnes_affiche": "26.9k",
    "secteur": "estheticienne",
    "email_contact": "amanda@grapperagency.com",
    "tarif_estime": "150-300€",
    "statut": "à_contacter",
    "dans_cible": true,
    "source": "modash",
    "date_contact": null,
    "scraped_at": "2026-05-14T19:05:54.046Z"
  },
  {
    "instagram_handle": "@emnooou",
    "twitter_handle": null,
    "nom": "EMNOU",
    "bio": "Glow Up, Beauty and Girls Things 🎀 💌 : emnoou@gmail.com Tiktok : emnouuuuu (+950K) Snapchat : emnouglowup",
    "ville": "Paris",
    "abonnes_instagram": 61100,
    "abonnes_affiche": "61.1k",
    "secteur": "estheticienne",
    "email_contact": "emnoou@gmail.com",
    "tarif_estime": "300-600€",
    "statut": "à_contacter",
    "dans_cible": true,
    "source": "modash",
    "date_contact": null,
    "scraped_at": "2026-05-14T19:05:54.047Z"
  },
  {
    "instagram_handle": "@nicolasdenoun",
    "twitter_handle": null,
    "nom": "Nicolas Denoun",
    "bio": "☆ Celebrity/beauty/fashion hair & make up artist ☆ nicolas@e-idols.com 📩",
    "ville": "Paris",
    "abonnes_instagram": 49700,
    "abonnes_affiche": "49.7k",
    "secteur": "estheticienne",
    "email_contact": "nicolas@e-idols.com",
    "tarif_estime": "150-300€",
    "statut": "à_contacter",
    "dans_cible": true,
    "source": "modash",
    "date_contact": null,
    "scraped_at": "2026-05-14T19:05:54.047Z"
  },
  {
    "instagram_handle": "@dolcetracy_",
    "twitter_handle": null,
    "nom": "Dolce Tracy",
    "bio": "Fashion, Glow & Style ᥫ᭡ ➔ Better life is coming ⏳ pro : ✉️ dolcetracy.contact@gmail.com Montpellier. South France",
    "ville": "France",
    "abonnes_instagram": 46700,
    "abonnes_affiche": "46.7k",
    "secteur": "estheticienne",
    "email_contact": "dolcetracy.contact@gmail.com",
    "tarif_estime": "150-300€",
    "statut": "à_contacter",
    "dans_cible": true,
    "source": "modash",
    "date_contact": null,
    "scraped_at": "2026-05-14T19:05:54.047Z"
  },
  {
    "instagram_handle": "@by_leila_",
    "twitter_handle": null,
    "nom": "Un Peu de Moi By Leila",
    "bio": "▪️MakeUp Artiste | SelfCare | Beauty Tips ▪️Life Style | Food | Nature Lover ▪️Locs 4 ans 📍guadeloupe •Partenariat : unpeudemoibyleila@gmail.com",
    "ville": "Paris",
    "abonnes_instagram": 32400,
    "abonnes_affiche": "32.4k",
    "secteur": "estheticienne",
    "email_contact": "unpeudemoibyleila@gmail.com",
    "tarif_estime": "150-300€",
    "statut": "à_contacter",
    "dans_cible": true,
    "source": "modash",
    "date_contact": null,
    "scraped_at": "2026-05-14T19:05:54.047Z"
  },
  {
    "instagram_handle": "@kaisou260218",
    "twitter_handle": null,
    "nom": "Armelle d",
    "bio": "Maman 4 enfants 3😻et 3🐶 #skincare #lifestyle #beauty Collab : armelledieda78520@gmail.com ou DM",
    "ville": "Paris",
    "abonnes_instagram": 31400,
    "abonnes_affiche": "31.4k",
    "secteur": "estheticienne",
    "email_contact": "armelledieda78520@gmail.com",
    "tarif_estime": "150-300€",
    "statut": "à_contacter",
    "dans_cible": true,
    "source": "modash",
    "date_contact": null,
    "scraped_at": "2026-05-14T19:05:54.047Z"
  },
  {
    "instagram_handle": "@emmaaunaturel",
    "twitter_handle": null,
    "nom": "Emma ✞",
    "bio": "T’aider à vivre plus sainement ✨🌱🌼 •Remèdes naturels || Phytothérapie || Food •💌Collab : emma.aunaturel@outlook.fr •Ebook santé féminine 👇🏻",
    "ville": "Paris",
    "abonnes_instagram": 74000,
    "abonnes_affiche": "74.0k",
    "secteur": "restaurant",
    "email_contact": "emma.aunaturel@outlook.fr",
    "tarif_estime": "300-600€",
    "statut": "à_contacter",
    "dans_cible": true,
    "source": "modash",
    "date_contact": null,
    "scraped_at": "2026-05-14T19:05:54.046Z"
  },
  {
    "instagram_handle": "@estherdsza",
    "twitter_handle": null,
    "nom": "Esther de Souza",
    "bio": "I love Food , Life & Sport 100% Vivante Pro: esther@adcrew-paris.com ⬇️Précommande mon livre ⬇️",
    "ville": "Paris",
    "abonnes_instagram": 64200,
    "abonnes_affiche": "64.2k",
    "secteur": "restaurant",
    "email_contact": "esther@adcrew-paris.com",
    "tarif_estime": "300-600€",
    "statut": "à_contacter",
    "dans_cible": true,
    "source": "modash",
    "date_contact": null,
    "scraped_at": "2026-05-14T19:05:54.046Z"
  },
  {
    "instagram_handle": "@maiacha_",
    "twitter_handle": null,
    "nom": "Maïa Chä 🌻(ex Petits Béguins)",
    "bio": "FREELANCE photo, vidéo, stopmotion Food • Lifestyle • Travel -> bonjour@maiacha.fr 💛☀️🌻😊",
    "ville": "Paris",
    "abonnes_instagram": 63700,
    "abonnes_affiche": "63.7k",
    "secteur": "restaurant",
    "email_contact": "bonjour@maiacha.fr",
    "tarif_estime": "300-600€",
    "statut": "à_contacter",
    "dans_cible": true,
    "source": "modash",
    "date_contact": null,
    "scraped_at": "2026-05-14T19:05:54.046Z"
  },
  {
    "instagram_handle": "@lescolonnesdesarah",
    "twitter_handle": null,
    "nom": "Sarah",
    "bio": "Fashion & Food 💻UGC creator & Freelance CM 👩🏻‍🍳Founder of @sarahskitchen.paris 📩 lescolonnesdesarah@gmail.com 📍Paris ⬇️Mon eBook - SARAH’S KITCHEN",
    "ville": "Paris",
    "abonnes_instagram": 54100,
    "abonnes_affiche": "54.1k",
    "secteur": "restaurant",
    "email_contact": "lescolonnesdesarah@gmail.com",
    "tarif_estime": "300-600€",
    "statut": "à_contacter",
    "dans_cible": true,
    "source": "modash",
    "date_contact": null,
    "scraped_at": "2026-05-14T19:05:54.046Z"
  },
  {
    "instagram_handle": "@larryaupaysdesmerguez",
    "twitter_handle": null,
    "nom": "Larry aux Pays des Merguez",
    "bio": "📝 I Food & autres plaisirs 🌎 I Paris & IDF & WW 🛜 I TikTok 1.5M / YT 117K 💡 I Decouverte 🚧 | Freelance ✉️ | larrycollaboration@gmail.com",
    "ville": "Paris",
    "abonnes_instagram": 29200,
    "abonnes_affiche": "29.2k",
    "secteur": "restaurant",
    "email_contact": "larrycollaboration@gmail.com",
    "tarif_estime": "150-300€",
    "statut": "à_contacter",
    "dans_cible": true,
    "source": "modash",
    "date_contact": null,
    "scraped_at": "2026-05-14T19:05:54.046Z"
  },
  {
    "instagram_handle": "@salmaberradafoodie",
    "twitter_handle": null,
    "nom": "Salma Berrada",
    "bio": "Je vis d’amour, de croissant et d’eau fraîche CAP boulangerie loading 🥖 🇫🇷Paris📍 Contact : salmaberradafoodie@gmail.com",
    "ville": "Paris",
    "abonnes_instagram": 26100,
    "abonnes_affiche": "26.1k",
    "secteur": "restaurant",
    "email_contact": "salmaberradafoodie@gmail.com",
    "tarif_estime": "150-300€",
    "statut": "à_contacter",
    "dans_cible": true,
    "source": "modash",
    "date_contact": null,
    "scraped_at": "2026-05-14T19:05:54.046Z"
  },
  {
    "instagram_handle": "@morganesoucramanienoff",
    "twitter_handle": null,
    "nom": "𝓜𝓸 (pour les intimes)",
    "bio": "tiré d’une histoire vraie 💫 modeling - lifestyle - travel - fit - food & much more 💌 soucramanien.morgane@gmail.com PARIS | REUNION",
    "ville": "Paris",
    "abonnes_instagram": 77000,
    "abonnes_affiche": "77.0k",
    "secteur": "restaurant",
    "email_contact": "soucramanien.morgane@gmail.com",
    "tarif_estime": "300-600€",
    "statut": "à_contacter",
    "dans_cible": true,
    "source": "modash",
    "date_contact": null,
    "scraped_at": "2026-05-14T19:05:54.047Z"
  },
  {
    "instagram_handle": "@monsieurcherii",
    "twitter_handle": null,
    "nom": "𝑀𝑜𝓃𝓈𝒾𝑒𝓊𝓇 𝒞𝒽𝑒́𝓇𝒾",
    "bio": "🍴 50 % food | 50 % life(sans)style✈️ 🐟 Pesco-végé 🎤 J’expérimente, je teste, je partage 🐶 J’ai un chien bavard 📍Paris 📩 monsieur.cheri.rs@gmail.com",
    "ville": "Paris",
    "abonnes_instagram": 52900,
    "abonnes_affiche": "52.9k",
    "secteur": "restaurant",
    "email_contact": "monsieur.cheri.rs@gmail.com",
    "tarif_estime": "300-600€",
    "statut": "à_contacter",
    "dans_cible": true,
    "source": "modash",
    "date_contact": null,
    "scraped_at": "2026-05-14T19:05:54.047Z"
  },
  {
    "instagram_handle": "@jbaptistebc",
    "twitter_handle": null,
    "nom": "Jean-Baptiste Biancarelli",
    "bio": "Un parisien fashion lol mngmt: @melchiorcarissimocommunication ✉️ jbaptistebc.pro@gmail.com Vlogs, tenues et ma vision de la mode",
    "ville": "Paris",
    "abonnes_instagram": 66900,
    "abonnes_affiche": "66.9k",
    "secteur": "salon_coiffure",
    "email_contact": "jbaptistebc.pro@gmail.com",
    "tarif_estime": "300-600€",
    "statut": "à_contacter",
    "dans_cible": true,
    "source": "modash",
    "date_contact": null,
    "scraped_at": "2026-05-14T19:05:54.047Z"
  },
  {
    "instagram_handle": "@florecita.hsl",
    "twitter_handle": null,
    "nom": "Flore 🌻",
    "bio": "Lille, Paris & Biarritz fashion, travel and ocean lifestyle 💌 flore.hesselpro@gmail.com",
    "ville": "Paris",
    "abonnes_instagram": 63700,
    "abonnes_affiche": "63.7k",
    "secteur": "salon_coiffure",
    "email_contact": "flore.hesselpro@gmail.com",
    "tarif_estime": "300-600€",
    "statut": "à_contacter",
    "dans_cible": true,
    "source": "modash",
    "date_contact": null,
    "scraped_at": "2026-05-14T19:05:54.047Z"
  },
  {
    "instagram_handle": "@camilleclnt",
    "twitter_handle": null,
    "nom": "Camille",
    "bio": "from Paris camilleclntpro@gmail.com lifestyle, fashion & travel mom of B 🤍",
    "ville": "Paris",
    "abonnes_instagram": 59800,
    "abonnes_affiche": "59.8k",
    "secteur": "salon_coiffure",
    "email_contact": "camilleclntpro@gmail.com",
    "tarif_estime": "300-600€",
    "statut": "à_contacter",
    "dans_cible": true,
    "source": "modash",
    "date_contact": null,
    "scraped_at": "2026-05-14T19:05:54.047Z"
  },
  {
    "instagram_handle": "@lifestyle_byju",
    "twitter_handle": null,
    "nom": "𝙹𝚄𝚂𝚃𝙸𝙽𝙴 ✨",
    "bio": "* Paris * 💌 Collab : justine.ppro@hotmail.com * Lifestyle | Fitness | Mode | Food ・❥・ * 𝔱𝔯𝔲𝔰𝔱 𝔱𝔥𝔢 𝔭𝔯𝔬𝔠𝔢𝔰𝔰 ➺",
    "ville": "Paris",
    "abonnes_instagram": 14000,
    "abonnes_affiche": "14.0k",
    "secteur": "spa",
    "email_contact": "justine.ppro@hotmail.com",
    "tarif_estime": "50-150€",
    "statut": "à_contacter",
    "dans_cible": true,
    "source": "modash",
    "date_contact": null,
    "scraped_at": "2026-05-14T19:05:54.047Z"
  },
  {
    "instagram_handle": "@clochette11",
    "twitter_handle": null,
    "nom": "Chloé V.",
    "bio": "From Paris 🏢 to La Ciotat 🏖 💌 clochette11ig@outlook.fr",
    "ville": "Paris",
    "abonnes_instagram": 11100,
    "abonnes_affiche": "11.1k",
    "secteur": "spa",
    "email_contact": "clochette11ig@outlook.fr",
    "tarif_estime": "50-150€",
    "statut": "à_contacter",
    "dans_cible": true,
    "source": "modash",
    "date_contact": null,
    "scraped_at": "2026-05-14T19:05:54.047Z"
  },
  {
    "instagram_handle": "@margo_gomart",
    "twitter_handle": null,
    "nom": "MARGO | ⚔️🥷🏻🔥",
    "bio": "Ta sista qui te veut du (VRAI) bien 🌙SPIRITUALITY | FITNESS | MUMLIFE✨ • Founder @timehers • Designer @elmi.atelier 💌Margo.gomart@gmail.com",
    "ville": "Paris",
    "abonnes_instagram": 10900,
    "abonnes_affiche": "10.9k",
    "secteur": "spa",
    "email_contact": "margo.gomart@gmail.com",
    "tarif_estime": "50-150€",
    "statut": "à_contacter",
    "dans_cible": true,
    "source": "modash",
    "date_contact": null,
    "scraped_at": "2026-05-14T19:05:54.047Z"
  },
  {
    "instagram_handle": "@charlesfit_ness",
    "twitter_handle": null,
    "nom": "Charles Fitness",
    "bio": "👨🏻‍🍳 Insta cuisine @fastgoodcuisine 📩 Contact : Charlesgc.fit@gmail.com",
    "ville": "Paris",
    "abonnes_instagram": 59400,
    "abonnes_affiche": "59.4k",
    "secteur": "spa",
    "email_contact": "charlesgc.fit@gmail.com",
    "tarif_estime": "300-600€",
    "statut": "à_contacter",
    "dans_cible": true,
    "source": "modash",
    "date_contact": null,
    "scraped_at": "2026-05-14T19:05:54.047Z"
  },
  {
    "instagram_handle": "@jeannefitglow",
    "twitter_handle": null,
    "nom": "Jeanne 🌺🥥✨",
    "bio": "🎧 fitness, mindset & feminité @biotechusa_fr code JENZO15 💌 jeannefitglow@gmail.com Mes programmes 🍑⬇️",
    "ville": "Paris",
    "abonnes_instagram": 56000,
    "abonnes_affiche": "56.0k",
    "secteur": "spa",
    "email_contact": "jeannefitglow@gmail.com",
    "tarif_estime": "300-600€",
    "statut": "à_contacter",
    "dans_cible": true,
    "source": "modash",
    "date_contact": null,
    "scraped_at": "2026-05-14T19:05:54.047Z"
  },
  {
    "instagram_handle": "@haessy_gwendal",
    "twitter_handle": null,
    "nom": "Gwendal Haessy",
    "bio": "gwendalhaessy.pro@gmail.com",
    "ville": "Paris",
    "abonnes_instagram": 23200,
    "abonnes_affiche": "23.2k",
    "secteur": "spa",
    "email_contact": "gwendalhaessy.pro@gmail.com",
    "tarif_estime": "150-300€",
    "statut": "à_contacter",
    "dans_cible": true,
    "source": "modash",
    "date_contact": null,
    "scraped_at": "2026-05-14T19:05:54.047Z"
  },
  {
    "instagram_handle": "@lolo_jea",
    "twitter_handle": null,
    "nom": "Lorine Jean",
    "bio": "🏋🏽‍♀️Coach sportif 🎥Youtube: lolo_jea 📲TikTok: lolo_jeaa 📩 Préparation physique moto: sobek.fitnesspro@gmail.com",
    "ville": "Paris",
    "abonnes_instagram": 17600,
    "abonnes_affiche": "17.6k",
    "secteur": "spa",
    "email_contact": "sobek.fitnesspro@gmail.com",
    "tarif_estime": "50-150€",
    "statut": "à_contacter",
    "dans_cible": true,
    "source": "modash",
    "date_contact": null,
    "scraped_at": "2026-05-14T19:05:54.047Z"
  },
  {
    "instagram_handle": "@eckenoff",
    "twitter_handle": null,
    "nom": "Ｓｕｎｎｙ Ｂａｂｙ 🌻",
    "bio": "🌞🌺🌊🐚🥥🏝️🏄🏼‍♀️ gym | tips | divertissement Coach sportive @esncom.fr : ECKENOFF @sunnybabytour 🩵 collab:eckenoff@gmail.com Demandes de suivie👇🏼",
    "ville": "Paris",
    "abonnes_instagram": 15700,
    "abonnes_affiche": "15.7k",
    "secteur": "spa",
    "email_contact": "eckenoff@gmail.com",
    "tarif_estime": "50-150€",
    "statut": "à_contacter",
    "dans_cible": true,
    "source": "modash",
    "date_contact": null,
    "scraped_at": "2026-05-14T19:05:54.047Z"
  },
  {
    "instagram_handle": "@corentinelj",
    "twitter_handle": null,
    "nom": "Corentine | Créatrice de contenu",
    "bio": "𝗖𝗿𝗲́𝗮𝘁𝗿𝗶𝗰𝗲 𝗱𝗲 𝗰𝗼𝗻𝘁𝗲𝗻𝘂 & 𝗨𝗚𝗖 Paris - Certifiée ARPP Collab : Mode • Sport • Bien-être Contact : corentineljpro@gmail.com",
    "ville": "Paris",
    "abonnes_instagram": 14900,
    "abonnes_affiche": "14.9k",
    "secteur": "spa",
    "email_contact": "corentineljpro@gmail.com",
    "tarif_estime": "50-150€",
    "statut": "à_contacter",
    "dans_cible": true,
    "source": "modash",
    "date_contact": null,
    "scraped_at": "2026-05-14T19:05:54.047Z"
  },
  {
    "instagram_handle": "@juliettedecore",
    "twitter_handle": null,
    "nom": "Juliette Décore",
    "bio": "Décoration intérieure Paris | Partenariat contact",
    "ville": "Paris",
    "abonnes_instagram": 12000,
    "abonnes_affiche": "12.0k",
    "secteur": "architecte_interieur",
    "email_contact": null,
    "tarif_estime": "50-150€",
    "statut": "ig_trouvé",
    "dans_cible": true,
    "source": "seed_architecte",
    "date_contact": null,
    "scraped_at": "2026-05-14T19:05:54.047Z"
  },
  {
    "instagram_handle": "@heju_paris",
    "twitter_handle": null,
    "nom": "Hélène & Julien - Heju",
    "bio": "Architectes intérieur Paris | Collaborations",
    "ville": "Paris",
    "abonnes_instagram": 45000,
    "abonnes_affiche": "45.0k",
    "secteur": "architecte_interieur",
    "email_contact": null,
    "tarif_estime": "150-300€",
    "statut": "ig_trouvé",
    "dans_cible": true,
    "source": "seed_architecte",
    "date_contact": null,
    "scraped_at": "2026-05-14T19:05:54.047Z"
  },
  {
    "instagram_handle": "@chiara.deco",
    "twitter_handle": null,
    "nom": "Chiara Déco",
    "bio": "Home decor | Paris | partenariat@gmail.com",
    "ville": "Paris",
    "abonnes_instagram": 15000,
    "abonnes_affiche": "15.0k",
    "secteur": "architecte_interieur",
    "email_contact": null,
    "tarif_estime": "50-150€",
    "statut": "ig_trouvé",
    "dans_cible": true,
    "source": "seed_architecte",
    "date_contact": null,
    "scraped_at": "2026-05-14T19:05:54.047Z"
  },
  {
    "instagram_handle": "@decorationinterieur.fr",
    "twitter_handle": null,
    "nom": "Décoration Intérieur France",
    "bio": "Inspiration déco France",
    "ville": "France",
    "abonnes_instagram": 22000,
    "abonnes_affiche": "22.0k",
    "secteur": "architecte_interieur",
    "email_contact": null,
    "tarif_estime": "150-300€",
    "statut": "ig_trouvé",
    "dans_cible": true,
    "source": "seed_architecte",
    "date_contact": null,
    "scraped_at": "2026-05-14T19:05:54.047Z"
  },
  {
    "instagram_handle": "@f4male",
    "twitter_handle": null,
    "nom": "your safe place ౨ৎ",
    "bio": "૮₍ ˃ ⤙ ˂ ₎ა «爱 — chiro ෆ ./づᡕᠵ᠊ᡃ່࡚ࠢ࠘ ⸝່ࠡࠣ᠊߯᠆ࠣ࠘ᡁࠣ࠘᠊᠊l~ ୭̥⋆*｡❄️",
    "ville": "Paris",
    "abonnes_instagram": 37600,
    "abonnes_affiche": "37.6k",
    "secteur": "clinique_esthetique",
    "email_contact": null,
    "tarif_estime": "150-300€",
    "statut": "ig_trouvé",
    "dans_cible": true,
    "source": "modash",
    "date_contact": null,
    "scraped_at": "2026-05-14T19:05:54.047Z"
  },
  {
    "instagram_handle": "@migmiglife",
    "twitter_handle": null,
    "nom": "Miguel M",
    "bio": "👑 @comite_beauty_pulpeux 📧 Créateur UGC Papa d’une Baby Queen 👸🏻 🔸#gpa 🔸#skincare 🔸#food 🔸#lifestyle",
    "ville": "Paris",
    "abonnes_instagram": 35100,
    "abonnes_affiche": "35.1k",
    "secteur": "clinique_esthetique",
    "email_contact": null,
    "tarif_estime": "150-300€",
    "statut": "ig_trouvé",
    "dans_cible": true,
    "source": "modash",
    "date_contact": null,
    "scraped_at": "2026-05-14T19:05:54.047Z"
  },
  {
    "instagram_handle": "@supersassa34220",
    "twitter_handle": null,
    "nom": "🦋Vanessa 🦋Créatrice beauté & mode",
    "bio": "✨ Beauté, mode & lifestyle au quotidien 👜 Shoes, sacs & skincare 🌷 Contenus doux, girly 📍 Occitanie là où le soleil brille ☀️",
    "ville": "Paris",
    "abonnes_instagram": 18600,
    "abonnes_affiche": "18.6k",
    "secteur": "clinique_esthetique",
    "email_contact": null,
    "tarif_estime": "50-150€",
    "statut": "ig_trouvé",
    "dans_cible": true,
    "source": "modash",
    "date_contact": null,
    "scraped_at": "2026-05-14T19:05:54.047Z"
  },
  {
    "instagram_handle": "@oceanekarol",
    "twitter_handle": null,
    "nom": "Oceane",
    "bio": "Makeup - Skincare - Tech - Lifestyle Tests, tendances & découvertes 📩 Collabs : DM ou Mail 🇫🇷 📍Alsace 📍Var",
    "ville": "Paris",
    "abonnes_instagram": 16600,
    "abonnes_affiche": "16.6k",
    "secteur": "clinique_esthetique",
    "email_contact": null,
    "tarif_estime": "50-150€",
    "statut": "ig_trouvé",
    "dans_cible": true,
    "source": "modash",
    "date_contact": null,
    "scraped_at": "2026-05-14T19:05:54.047Z"
  },
  {
    "instagram_handle": "@jamilanfds",
    "twitter_handle": null,
    "nom": "Jamila nfds",
    "bio": "Découverte & Partage Fragrance & Skincare & Makeup & Lifestyle",
    "ville": "Paris",
    "abonnes_instagram": 16400,
    "abonnes_affiche": "16.4k",
    "secteur": "clinique_esthetique",
    "email_contact": null,
    "tarif_estime": "50-150€",
    "statut": "ig_trouvé",
    "dans_cible": true,
    "source": "modash",
    "date_contact": null,
    "scraped_at": "2026-05-14T19:05:54.047Z"
  },
  {
    "instagram_handle": "@delfine_51",
    "twitter_handle": null,
    "nom": "𝐷𝑒𝑙𝑝ℎ𝑖𝑛𝑒",
    "bio": "💄 𝗠𝗮𝗸𝗲𝘂𝗽 | 𝘀𝗸𝗶𝗻𝗰𝗮𝗿𝗲 | 𝗹𝗶𝗳𝗲𝘀𝘁𝘆𝗹𝗲 🇫🇷 𝗠𝗮𝗿𝗻𝗲, 𝗙𝗿𝗮𝗻𝗰𝗲 🎀 𝟮 𝗽𝗿𝗶𝗻𝗰𝗲𝘀𝘀𝗲𝘀",
    "ville": "Paris",
    "abonnes_instagram": 14900,
    "abonnes_affiche": "14.9k",
    "secteur": "clinique_esthetique",
    "email_contact": null,
    "tarif_estime": "50-150€",
    "statut": "ig_trouvé",
    "dans_cible": true,
    "source": "modash",
    "date_contact": null,
    "scraped_at": "2026-05-14T19:05:54.047Z"
  },
  {
    "instagram_handle": "@lifebyfanny_m",
    "twitter_handle": null,
    "nom": "Fanny Miosotis",
    "bio": "☀️ Positivité • Partage • Image de soi 🎀 Rémission cancer du sein 👩🏻‍🦲 Créatrice de @maquillemonkrane 💄 Makeup @makeupbyfanny_m 📍 Paris",
    "ville": "Paris",
    "abonnes_instagram": 13600,
    "abonnes_affiche": "13.6k",
    "secteur": "clinique_esthetique",
    "email_contact": null,
    "tarif_estime": "50-150€",
    "statut": "ig_trouvé",
    "dans_cible": true,
    "source": "modash",
    "date_contact": null,
    "scraped_at": "2026-05-14T19:05:54.047Z"
  },
  {
    "instagram_handle": "@ingridlaurenn",
    "twitter_handle": null,
    "nom": "Ingrid Lauren",
    "bio": "Beauty | Lifestyle | Mode 🇲🇶 | Paris | World ✨ @madamelittre",
    "ville": "Paris",
    "abonnes_instagram": 73600,
    "abonnes_affiche": "73.6k",
    "secteur": "estheticienne",
    "email_contact": null,
    "tarif_estime": "300-600€",
    "statut": "ig_trouvé",
    "dans_cible": true,
    "source": "modash",
    "date_contact": null,
    "scraped_at": "2026-05-14T19:05:54.046Z"
  },
  {
    "instagram_handle": "@illustrations.byeva",
    "twitter_handle": null,
    "nom": "Eva • Beauty & Brand Illustrator 🇬🇧🇫🇷🇦🇪",
    "bio": "💄 Beauty & Brand Illustrator ✨ Custom illustrations for beauty, fashion & lifestyle brands 🌸 +1000 clients worldwide ⬇️ Shop & commissions ↓",
    "ville": "Paris",
    "abonnes_instagram": 73500,
    "abonnes_affiche": "73.5k",
    "secteur": "estheticienne",
    "email_contact": null,
    "tarif_estime": "300-600€",
    "statut": "ig_trouvé",
    "dans_cible": true,
    "source": "modash",
    "date_contact": null,
    "scraped_at": "2026-05-14T19:05:54.046Z"
  },
  {
    "instagram_handle": "@thomaslavellephotography",
    "twitter_handle": null,
    "nom": "Thomas Lavelle",
    "bio": "FASHION PHOTOGRAPHER based in Paris Style over fashion Attitude over beauty Strength over cuteness Denim over silk",
    "ville": "Paris",
    "abonnes_instagram": 58200,
    "abonnes_affiche": "58.2k",
    "secteur": "estheticienne",
    "email_contact": null,
    "tarif_estime": "300-600€",
    "statut": "ig_trouvé",
    "dans_cible": true,
    "source": "modash",
    "date_contact": null,
    "scraped_at": "2026-05-14T19:05:54.046Z"
  },
  {
    "instagram_handle": "@bibi____home",
    "twitter_handle": null,
    "nom": "Gaby 🇫🇷 Visual stylist | Set designer",
    "bio": "⊹ ⊹ ⊹ ⊹ Home decor ideas for a French eclectic style 🦚 Interior styling • Art 📸 I see beauty in everything",
    "ville": "Paris",
    "abonnes_instagram": 40100,
    "abonnes_affiche": "40.1k",
    "secteur": "estheticienne",
    "email_contact": null,
    "tarif_estime": "150-300€",
    "statut": "ig_trouvé",
    "dans_cible": true,
    "source": "modash",
    "date_contact": null,
    "scraped_at": "2026-05-14T19:05:54.046Z"
  },
  {
    "instagram_handle": "@arnaudsoldourdin",
    "twitter_handle": null,
    "nom": "Arnaud Sol Dourdin",
    "bio": "💄 makeup artist . Beauty Fashion Celebrities. Créateur du filtre pastel 📍French Paris 📧 Fashion / beauty / Editorial",
    "ville": "Paris",
    "abonnes_instagram": 39100,
    "abonnes_affiche": "39.1k",
    "secteur": "estheticienne",
    "email_contact": null,
    "tarif_estime": "150-300€",
    "statut": "ig_trouvé",
    "dans_cible": true,
    "source": "modash",
    "date_contact": null,
    "scraped_at": "2026-05-14T19:05:54.046Z"
  },
  {
    "instagram_handle": "@fadelahaaaa",
    "twitter_handle": null,
    "nom": "Fadela 🫶🏼✨",
    "bio": "✨ STYLE, HAS NO SIZE ✨",
    "ville": "Paris",
    "abonnes_instagram": 22200,
    "abonnes_affiche": "22.2k",
    "secteur": "estheticienne",
    "email_contact": null,
    "tarif_estime": "150-300€",
    "statut": "ig_trouvé",
    "dans_cible": true,
    "source": "modash",
    "date_contact": null,
    "scraped_at": "2026-05-14T19:05:54.046Z"
  },
  {
    "instagram_handle": "@marion_lareunionnaiz",
    "twitter_handle": null,
    "nom": "Marion 🌺",
    "bio": "𝐋𝐚 𝐑𝐞𝐮𝐧𝐢𝐨𝐧𝐧𝐚𝐢𝐳 🌺🌴☀️💍 ° 𝓂𝒶𝓇𝒾𝑜𝓃𝓁𝒶𝓇𝑒𝓊𝓃𝒾𝑜𝓃𝓃𝒶𝒾𝓏@𝑔𝓂𝒶𝒾𝓁.𝒸𝑜𝓂 ° ℬ𝑒𝓈𝓉 𝒾𝓃𝒻𝓁𝓊𝑒𝓃𝒸𝑒𝓇 𝒻𝒶𝓈𝒽𝒾𝑜𝓃 & 𝒷𝑒𝒶𝓊𝓉𝓎 𝑜𝒸é𝒶𝓃 𝒾𝓃𝒹𝒾𝑒𝓃 👗",
    "ville": "Paris",
    "abonnes_instagram": 67300,
    "abonnes_affiche": "67.3k",
    "secteur": "estheticienne",
    "email_contact": null,
    "tarif_estime": "300-600€",
    "statut": "ig_trouvé",
    "dans_cible": true,
    "source": "modash",
    "date_contact": null,
    "scraped_at": "2026-05-14T19:05:54.047Z"
  },
  {
    "instagram_handle": "@khevi_na",
    "twitter_handle": null,
    "nom": "Khevi_na",
    "bio": "Créatrice de contenu et de bonne humeur en autodérision Mood Lifestyle Beauty Testeuse de produit Ici que du positif #partenariat en M.P ❤️‍🩹",
    "ville": "Paris",
    "abonnes_instagram": 55600,
    "abonnes_affiche": "55.6k",
    "secteur": "estheticienne",
    "email_contact": null,
    "tarif_estime": "300-600€",
    "statut": "ig_trouvé",
    "dans_cible": true,
    "source": "modash",
    "date_contact": null,
    "scraped_at": "2026-05-14T19:05:54.047Z"
  },
  {
    "instagram_handle": "@hailey_hln",
    "twitter_handle": null,
    "nom": "Hailey",
    "bio": "Where beauty meets real life, and chaos wears lipstick 💋 👩🏽‍💻Content strategist • Beauty & lifestyle creator 📍Martinique ⇄ Anywhere success calls",
    "ville": "Paris",
    "abonnes_instagram": 42300,
    "abonnes_affiche": "42.3k",
    "secteur": "estheticienne",
    "email_contact": null,
    "tarif_estime": "150-300€",
    "statut": "ig_trouvé",
    "dans_cible": true,
    "source": "modash",
    "date_contact": null,
    "scraped_at": "2026-05-14T19:05:54.047Z"
  },
  {
    "instagram_handle": "@les_envies_d_elya",
    "twitter_handle": null,
    "nom": "Elya - Mode Beauté Lifestyle",
    "bio": "🇱🇧🇫🇷 Pharmacist 🧪 ⭐️certifiée ARPP🆗 Lifestyle, Fashion & Beauty 💜💙💖 🎁 pleins de #concours à vous proposer 📍Paris 📩 Email Me for Collab",
    "ville": "Paris",
    "abonnes_instagram": 41000,
    "abonnes_affiche": "41.0k",
    "secteur": "estheticienne",
    "email_contact": null,
    "tarif_estime": "150-300€",
    "statut": "ig_trouvé",
    "dans_cible": true,
    "source": "modash",
    "date_contact": null,
    "scraped_at": "2026-05-14T19:05:54.047Z"
  },
  {
    "instagram_handle": "@amandaabagima_nutrition",
    "twitter_handle": null,
    "nom": "Amanda Abagima - Nutrition RSPH👩🏾‍🍳",
    "bio": "📙Mon livre : \"Cuisiner le monde sans sucre\" Précommande sur le lien 👇 🤤Des plats #sanssucres & #conseilsnutrition 🚀Coaching: groupe | individuel 📍🇬🇧🇧🇪",
    "ville": "Paris",
    "abonnes_instagram": 67600,
    "abonnes_affiche": "67.6k",
    "secteur": "restaurant",
    "email_contact": null,
    "tarif_estime": "300-600€",
    "statut": "ig_trouvé",
    "dans_cible": true,
    "source": "modash",
    "date_contact": null,
    "scraped_at": "2026-05-14T19:05:54.046Z"
  },
  {
    "instagram_handle": "@binliang.alexander.peng",
    "twitter_handle": null,
    "nom": "Binliang Alexander Peng, Binliang Peng",
    "bio": "French Jewellery Artisan, working with my mind, my hands and my heart on your story. I love Culture, Fashion & Food 🇫🇷 10 place Vendôme Paris, France.",
    "ville": "Paris",
    "abonnes_instagram": 59700,
    "abonnes_affiche": "59.7k",
    "secteur": "restaurant",
    "email_contact": null,
    "tarif_estime": "300-600€",
    "statut": "ig_trouvé",
    "dans_cible": true,
    "source": "modash",
    "date_contact": null,
    "scraped_at": "2026-05-14T19:05:54.046Z"
  },
  {
    "instagram_handle": "@manon.mange",
    "twitter_handle": null,
    "nom": "Manon • Food, sorties & escapades",
    "bio": "‎ ‎ ✨ Je déniche de bonnes adresses à Paris & IDF👇 ‎ ‎ 🍜 Restos, boulangeries, brunchs 🥐 ‎ ‎ 🚶🏻‍♀️ Et aussi des activités et escapades 🍃🎒",
    "ville": "Paris",
    "abonnes_instagram": 35200,
    "abonnes_affiche": "35.2k",
    "secteur": "restaurant",
    "email_contact": null,
    "tarif_estime": "150-300€",
    "statut": "ig_trouvé",
    "dans_cible": true,
    "source": "modash",
    "date_contact": null,
    "scraped_at": "2026-05-14T19:05:54.046Z"
  },
  {
    "instagram_handle": "@food.from.desire",
    "twitter_handle": null,
    "nom": "Marjorie",
    "bio": "Mode • Beauté • Food • Paris Lifestyle Adresses, looks & sélections Pour inspirer et accompagner ton quotidien",
    "ville": "Paris",
    "abonnes_instagram": 25700,
    "abonnes_affiche": "25.7k",
    "secteur": "restaurant",
    "email_contact": null,
    "tarif_estime": "150-300€",
    "statut": "ig_trouvé",
    "dans_cible": true,
    "source": "modash",
    "date_contact": null,
    "scraped_at": "2026-05-14T19:05:54.046Z"
  },
  {
    "instagram_handle": "@manuel.llorca.garcia",
    "twitter_handle": null,
    "nom": "Manuel Llorca Garcia",
    "bio": "De la cuisine méditerranéenne, du rugby, des copains, des rires… 🧿👨‍🍳🏋️‍♂️🎭🌞🧸🏉🌈@lesgaillards.paris Enfant du sud🌻 vit à Paris📍 🍝Mon blog cuisine ⤵️",
    "ville": "Paris",
    "abonnes_instagram": 24900,
    "abonnes_affiche": "24.9k",
    "secteur": "restaurant",
    "email_contact": null,
    "tarif_estime": "150-300€",
    "statut": "ig_trouvé",
    "dans_cible": true,
    "source": "modash",
    "date_contact": null,
    "scraped_at": "2026-05-14T19:05:54.046Z"
  },
  {
    "instagram_handle": "@shaa_minou",
    "twitter_handle": null,
    "nom": "Aude Salomé",
    "bio": "✨Todo lo que puedes imaginar es real 🦋 🌴Caribbean girl 🌸 from Martinique 🐚 📍Paris 🇫🇷 • México 🇲🇽",
    "ville": "Paris",
    "abonnes_instagram": 23500,
    "abonnes_affiche": "23.5k",
    "secteur": "restaurant",
    "email_contact": null,
    "tarif_estime": "150-300€",
    "statut": "ig_trouvé",
    "dans_cible": true,
    "source": "modash",
    "date_contact": null,
    "scraped_at": "2026-05-14T19:05:54.046Z"
  },
  {
    "instagram_handle": "@cook_vibes",
    "twitter_handle": null,
    "nom": "Pauline",
    "bio": "📝 | Partage de recettes 📍 | Découverte adresses food à Lille 🏃🏽‍♀️ | Campus (code : COOKVIBESRUN)",
    "ville": "Lille",
    "abonnes_instagram": 53700,
    "abonnes_affiche": "53.7k",
    "secteur": "restaurant",
    "email_contact": null,
    "tarif_estime": "300-600€",
    "statut": "ig_trouvé",
    "dans_cible": true,
    "source": "modash",
    "date_contact": null,
    "scraped_at": "2026-05-14T19:05:54.047Z"
  },
  {
    "instagram_handle": "@ruoteng_z",
    "twitter_handle": null,
    "nom": "占若腾",
    "bio": "Je fais des trucs drôles (parfois)🤪 dm for collab 📩",
    "ville": "Paris",
    "abonnes_instagram": 53700,
    "abonnes_affiche": "53.7k",
    "secteur": "restaurant",
    "email_contact": null,
    "tarif_estime": "300-600€",
    "statut": "ig_trouvé",
    "dans_cible": true,
    "source": "modash",
    "date_contact": null,
    "scraped_at": "2026-05-14T19:05:54.047Z"
  },
  {
    "instagram_handle": "@jamal.rosyne",
    "twitter_handle": null,
    "nom": "Jamal CHLEUH",
    "bio": "Votre Magasin ROSYNE CLUB (11h-19h) Votre Restaurant Bar Ambiance Le FIVE (19h-01h) à MONTPELLIER",
    "ville": "Paris",
    "abonnes_instagram": 73000,
    "abonnes_affiche": "73.0k",
    "secteur": "salon_coiffure",
    "email_contact": null,
    "tarif_estime": "300-600€",
    "statut": "ig_trouvé",
    "dans_cible": true,
    "source": "modash",
    "date_contact": null,
    "scraped_at": "2026-05-14T19:05:54.047Z"
  },
  {
    "instagram_handle": "@tresormbimbe",
    "twitter_handle": null,
    "nom": "Tresor Mbimbe",
    "bio": "Never give up on your dreams. Certified Fitness Coach GOD IS GOOD AND REAL ✝️🙏🏾",
    "ville": "Paris",
    "abonnes_instagram": 36300,
    "abonnes_affiche": "36.3k",
    "secteur": "spa",
    "email_contact": null,
    "tarif_estime": "150-300€",
    "statut": "ig_trouvé",
    "dans_cible": true,
    "source": "modash",
    "date_contact": null,
    "scraped_at": "2026-05-14T19:05:54.047Z"
  },
  {
    "instagram_handle": "@julieferrez_officiel",
    "twitter_handle": null,
    "nom": "Julie Ferrez",
    "bio": "Mange•Bouge•Rayonne☀️ Yoga • Fitness • Mindset Pionnière du bien-être depuis 20 ans Studio en ligne & retraites ⤹ 1er cours pour bouger sans pression",
    "ville": "Paris",
    "abonnes_instagram": 28300,
    "abonnes_affiche": "28.3k",
    "secteur": "spa",
    "email_contact": null,
    "tarif_estime": "150-300€",
    "statut": "ig_trouvé",
    "dans_cible": true,
    "source": "modash",
    "date_contact": null,
    "scraped_at": "2026-05-14T19:05:54.047Z"
  },
  {
    "instagram_handle": "@naeelife___",
    "twitter_handle": null,
    "nom": "NAEELIFE",
    "bio": "ＦＩＴＮＥＳＳ |ＬＩＦＥＳＴＹＬＥ|ＴＲＡＶＥＬ 🎀⏳🏋🏽‍♀️✈️",
    "ville": "Paris",
    "abonnes_instagram": 27000,
    "abonnes_affiche": "27.0k",
    "secteur": "spa",
    "email_contact": null,
    "tarif_estime": "150-300€",
    "statut": "ig_trouvé",
    "dans_cible": true,
    "source": "modash",
    "date_contact": null,
    "scraped_at": "2026-05-14T19:05:54.047Z"
  },
  {
    "instagram_handle": "@hmzelm",
    "twitter_handle": null,
    "nom": "Hamza",
    "bio": "Lawyer ⚖️ Fitness 🏋️‍♀️ Paris-based 🇫🇷🇲🇦 ♏️",
    "ville": "Paris",
    "abonnes_instagram": 17700,
    "abonnes_affiche": "17.7k",
    "secteur": "spa",
    "email_contact": null,
    "tarif_estime": "50-150€",
    "statut": "ig_trouvé",
    "dans_cible": true,
    "source": "modash",
    "date_contact": null,
    "scraped_at": "2026-05-14T19:05:54.047Z"
  },
  {
    "instagram_handle": "@clem_n_hama",
    "twitter_handle": null,
    "nom": "clem_n_hama",
    "bio": "Clément ☮ France, Paris 🇫🇷 PhD in pharmacy and Marketing 💉💊📊 Geek 🎮 & Fitness addict 🏋🏼‍♀️",
    "ville": "Paris",
    "abonnes_instagram": 8000,
    "abonnes_affiche": "8.0k",
    "secteur": "spa",
    "email_contact": null,
    "tarif_estime": "gratuit/produit",
    "statut": "ig_trouvé",
    "dans_cible": true,
    "source": "modash",
    "date_contact": null,
    "scraped_at": "2026-05-14T19:05:54.047Z"
  },
  {
    "instagram_handle": "@guillaume_koma",
    "twitter_handle": null,
    "nom": "Guillaume",
    "bio": "⚡️ Coach diplômé 🍼 @supersetnutrition l 20% l KOMA20 🫆Ambassadeur Fitness Park @fitnessparkniceverany 📍 Nice, Fr",
    "ville": "Nice",
    "abonnes_instagram": 25200,
    "abonnes_affiche": "25.2k",
    "secteur": "spa",
    "email_contact": null,
    "tarif_estime": "150-300€",
    "statut": "ig_trouvé",
    "dans_cible": true,
    "source": "modash",
    "date_contact": null,
    "scraped_at": "2026-05-14T19:05:54.047Z"
  },
  {
    "instagram_handle": "@anjela_cnn",
    "twitter_handle": null,
    "nom": "𝑨𝒏𝒋𝒆𝒍𝒂",
    "bio": "⁴⁴⁴ 𝑳𝒊𝒇𝒆𝒔𝒕𝒚𝒍𝒆 ~ 𝑭𝒊𝒕𝒏𝒆𝒔𝒔",
    "ville": "Paris",
    "abonnes_instagram": 14600,
    "abonnes_affiche": "14.6k",
    "secteur": "spa",
    "email_contact": null,
    "tarif_estime": "50-150€",
    "statut": "ig_trouvé",
    "dans_cible": true,
    "source": "modash",
    "date_contact": null,
    "scraped_at": "2026-05-14T19:05:54.047Z"
  },
  {
    "instagram_handle": "@vanessa24h",
    "twitter_handle": null,
    "nom": "Vanessa",
    "bio": "TESTS ET ACHATS DE PRODUITS VARIÉS #Beauty 💄 #skincare #fitness #hightech #lifestyle #mumlife COLLAB EN DM ✉️",
    "ville": "Paris",
    "abonnes_instagram": 11300,
    "abonnes_affiche": "11.3k",
    "secteur": "spa",
    "email_contact": null,
    "tarif_estime": "50-150€",
    "statut": "ig_trouvé",
    "dans_cible": true,
    "source": "modash",
    "date_contact": null,
    "scraped_at": "2026-05-14T19:05:54.047Z"
  },
  {
    "instagram_handle": "@julespedretti",
    "twitter_handle": null,
    "nom": "Jules Pedretti",
    "bio": "Le vrai Pacha ☁️🛁🧖🏻🥚 Skincare, riz & oeuf. Co-host @lespachas 🎙️ Contact : julespedretti@foll-ow.com",
    "ville": "Paris",
    "abonnes_instagram": 149400,
    "abonnes_affiche": "149.4k",
    "secteur": "clinique_esthetique",
    "email_contact": "julespedretti@foll-ow.com",
    "tarif_estime": "300-600€",
    "statut": "à_contacter",
    "dans_cible": false,
    "source": "modash",
    "date_contact": null,
    "scraped_at": "2026-05-14T19:05:54.047Z"
  },
  {
    "instagram_handle": "@lbslucie",
    "twitter_handle": null,
    "nom": "Lucie Labois 🧚🏻",
    "bio": "⋆𐙚˚⋆ 𝑳 𝑼 𝑪 𝑰 𝑬 🧚🏼⋆𝜗𝜚˚⋆ 🌷𝐔𝐧𝐞 𝐆𝐢𝐫𝐥𝐢𝐞 𝐪𝐮𝐢 𝐩𝐚𝐫𝐭𝐚𝐠𝐞 𝐬𝐚 𝐯𝐢𝐞 ! 🎀 𝚂𝚔𝚒𝚗𝚌𝚊𝚛𝚎 ⭒ 𝚖𝚊𝚔𝚎𝚞𝚙 ⭒ 𝚍𝚘𝚐 ⭒ 𝚛𝚎𝚗𝚘𝚟𝚊𝚝𝚒𝚘𝚗 📨 lucie@sunymanagement.com",
    "ville": "Paris",
    "abonnes_instagram": null,
    "abonnes_affiche": null,
    "secteur": "clinique_esthetique",
    "email_contact": "lucie@sunymanagement.com",
    "tarif_estime": "gratuit/produit",
    "statut": "à_contacter",
    "dans_cible": null,
    "source": "modash",
    "date_contact": null,
    "scraped_at": "2026-05-14T19:05:54.047Z"
  },
  {
    "instagram_handle": "@luciebonni",
    "twitter_handle": null,
    "nom": "Lucie🫰🏻",
    "bio": "32y💖 Marseille ☀️ Proud midsize🫶🏻 Mode, skincare & makeup addict🤠 50K TT: Luciebonni 🚀 luciemmmm@hotmail.com",
    "ville": "Marseille",
    "abonnes_instagram": 98800,
    "abonnes_affiche": "98.8k",
    "secteur": "clinique_esthetique",
    "email_contact": "luciemmmm@hotmail.com",
    "tarif_estime": "300-600€",
    "statut": "à_contacter",
    "dans_cible": false,
    "source": "modash",
    "date_contact": null,
    "scraped_at": "2026-05-14T19:05:54.047Z"
  },
  {
    "instagram_handle": "@lyana_isaac_tiago_models",
    "twitter_handle": null,
    "nom": "Floryse Beranto",
    "bio": "💫FLORYSE | UGC CREATOR | AUTEUR @agence_now_itsyou 🎬 You tube : Maman tout simplement (64k) TikTOK : GlossyFlo Collab 📩florysenicolas@hotmail.fr",
    "ville": "Paris",
    "abonnes_instagram": null,
    "abonnes_affiche": null,
    "secteur": "clinique_esthetique",
    "email_contact": "florysenicolas@hotmail.fr",
    "tarif_estime": "gratuit/produit",
    "statut": "à_contacter",
    "dans_cible": null,
    "source": "modash",
    "date_contact": null,
    "scraped_at": "2026-05-14T19:05:54.047Z"
  },
  {
    "instagram_handle": "@raphaelmetivet",
    "twitter_handle": null,
    "nom": "Raphael Metivet",
    "bio": "Capturing the beauty of Paris✨ 📸 Luxury hotels & interiors photographer 📩 raphael@futurmgmt.com Discover my prints of Paris:",
    "ville": "Paris",
    "abonnes_instagram": 479700,
    "abonnes_affiche": "479.7k",
    "secteur": "estheticienne",
    "email_contact": "raphael@futurmgmt.com",
    "tarif_estime": "300-600€",
    "statut": "à_contacter",
    "dans_cible": false,
    "source": "modash",
    "date_contact": null,
    "scraped_at": "2026-05-14T19:05:54.045Z"
  },
  {
    "instagram_handle": "@oceanemnta",
    "twitter_handle": null,
    "nom": "Océane",
    "bio": "Beauty & Lifestyle Mom of 1 👶🏾 📩: oceanemnta@gmail.com",
    "ville": "Paris",
    "abonnes_instagram": 228300,
    "abonnes_affiche": "228.3k",
    "secteur": "estheticienne",
    "email_contact": "oceanemnta@gmail.com",
    "tarif_estime": "300-600€",
    "statut": "à_contacter",
    "dans_cible": false,
    "source": "modash",
    "date_contact": null,
    "scraped_at": "2026-05-14T19:05:54.046Z"
  },
  {
    "instagram_handle": "@pariswithpamela",
    "twitter_handle": null,
    "nom": "PAMELA ✨ -LUXURY TRAVEL & LIFESTYLE•FASHION & BEAUTY",
    "bio": "🔎 HÔTELS,WELLNESS, GASTRONOMY📍PARIS certifiée ARPPUB📩 collaboration : belreplay@hotmail.com",
    "ville": "Paris",
    "abonnes_instagram": 179700,
    "abonnes_affiche": "179.7k",
    "secteur": "estheticienne",
    "email_contact": "belreplay@hotmail.com",
    "tarif_estime": "300-600€",
    "statut": "à_contacter",
    "dans_cible": false,
    "source": "modash",
    "date_contact": null,
    "scraped_at": "2026-05-14T19:05:54.046Z"
  },
  {
    "instagram_handle": "@soofiabnb",
    "twitter_handle": null,
    "nom": "Sofia",
    "bio": "que des Brain and Beauty ici - J’étudie la com et je fais des vidéos ⭐️🎬 @sciencespo | @assasuniversite 📚 sofiabnb@foll-ow.com💌 Paris, France",
    "ville": "Paris",
    "abonnes_instagram": 150000,
    "abonnes_affiche": "150.0k",
    "secteur": "estheticienne",
    "email_contact": "sofiabnb@foll-ow.com",
    "tarif_estime": "300-600€",
    "statut": "à_contacter",
    "dans_cible": false,
    "source": "modash",
    "date_contact": null,
    "scraped_at": "2026-05-14T19:05:54.046Z"
  },
  {
    "instagram_handle": "@clemence_allaire",
    "twitter_handle": null,
    "nom": "Clémence Allaire",
    "bio": "📱| Lifestyle / Fashion / Beauty 🐣l Mum of two boys 📍| Orléans - Sologne ⌨️| Collab : clemence@clemenceallaire.com",
    "ville": "Paris",
    "abonnes_instagram": 136400,
    "abonnes_affiche": "136.4k",
    "secteur": "estheticienne",
    "email_contact": "clemence@clemenceallaire.com",
    "tarif_estime": "300-600€",
    "statut": "à_contacter",
    "dans_cible": false,
    "source": "modash",
    "date_contact": null,
    "scraped_at": "2026-05-14T19:05:54.046Z"
  },
  {
    "instagram_handle": "@the.look.up_",
    "twitter_handle": null,
    "nom": "Thelookup",
    "bio": "Beauty hacks du basique au magique Coaching privé pour briller 📩 thelookupmakeup@gmail.com 🥐 Paris",
    "ville": "Paris",
    "abonnes_instagram": 98200,
    "abonnes_affiche": "98.2k",
    "secteur": "estheticienne",
    "email_contact": "thelookupmakeup@gmail.com",
    "tarif_estime": "300-600€",
    "statut": "à_contacter",
    "dans_cible": false,
    "source": "modash",
    "date_contact": null,
    "scraped_at": "2026-05-14T19:05:54.046Z"
  },
  {
    "instagram_handle": "@antastique",
    "twitter_handle": null,
    "nom": "Antastique",
    "bio": "ғʀᴀɢʀᴀɴᴄᴇs • ᴍᴏᴅᴇsᴛ ғᴀsʜɪᴏɴ • ʙᴇᴀᴜᴛʏ Owner of @soriahijab 📨antastique.collab@gmail.com Paris, with love ♡",
    "ville": "Paris",
    "abonnes_instagram": null,
    "abonnes_affiche": null,
    "secteur": "estheticienne",
    "email_contact": "antastique.collab@gmail.com",
    "tarif_estime": "gratuit/produit",
    "statut": "à_contacter",
    "dans_cible": null,
    "source": "modash",
    "date_contact": null,
    "scraped_at": "2026-05-14T19:05:54.046Z"
  },
  {
    "instagram_handle": "@diana.kmakeup",
    "twitter_handle": null,
    "nom": "Diana Kmakeup",
    "bio": "BEAUTY EXPERT / LIFESTYLE 💄COMPTE MUA @diana_kstudio 💌 diana@e-idols.com 📍Paris - Nancy",
    "ville": "Paris",
    "abonnes_instagram": 161000,
    "abonnes_affiche": "161.0k",
    "secteur": "estheticienne",
    "email_contact": "diana@e-idols.com",
    "tarif_estime": "300-600€",
    "statut": "à_contacter",
    "dans_cible": false,
    "source": "modash",
    "date_contact": null,
    "scraped_at": "2026-05-14T19:05:54.047Z"
  },
  {
    "instagram_handle": "@samantha_grv",
    "twitter_handle": null,
    "nom": "Samantha Gruvier",
    "bio": "♡ Maman d’Émilia | A ✨ ✿ Orléans ∝ Lifestyle, kids & beauty ⌇ Déco⌇Voyage 📩 contact@samanthagrv.com",
    "ville": "Paris",
    "abonnes_instagram": 83400,
    "abonnes_affiche": "83.4k",
    "secteur": "estheticienne",
    "email_contact": "contact@samanthagrv.com",
    "tarif_estime": "300-600€",
    "statut": "à_contacter",
    "dans_cible": false,
    "source": "modash",
    "date_contact": null,
    "scraped_at": "2026-05-14T19:05:54.047Z"
  },
  {
    "instagram_handle": "@morghane",
    "twitter_handle": null,
    "nom": "Morghane avec un h🎤",
    "bio": "☆ 𝗖𝗥𝗘𝗔𝗧𝗥𝗜𝗖𝗘 𝗗𝗘 𝗖𝗢𝗡𝗧𝗘𝗡𝗨 • 𝗨𝗚𝗖 ☆ • Fashion | Beauty | Lifestyle • ♡ Tiktok : morghane (+400K) → morghanecontactpro@gmail.com",
    "ville": "Paris",
    "abonnes_instagram": null,
    "abonnes_affiche": null,
    "secteur": "estheticienne",
    "email_contact": "morghanecontactpro@gmail.com",
    "tarif_estime": "gratuit/produit",
    "statut": "à_contacter",
    "dans_cible": null,
    "source": "modash",
    "date_contact": null,
    "scraped_at": "2026-05-14T19:05:54.047Z"
  },
  {
    "instagram_handle": "@_urbaneva",
    "twitter_handle": null,
    "nom": "Urban ₊ ⊹",
    "bio": "🥀 Alternative beauty/fashion youtuber Ma boutique : @cyberxunicorn 💌 urbanunicorn.lauryn@gmail.com horror and gym enthusiast ☠︎︎ ⋆₊ ♱",
    "ville": "Paris",
    "abonnes_instagram": null,
    "abonnes_affiche": null,
    "secteur": "estheticienne",
    "email_contact": "urbanunicorn.lauryn@gmail.com",
    "tarif_estime": "gratuit/produit",
    "statut": "à_contacter",
    "dans_cible": null,
    "source": "modash",
    "date_contact": null,
    "scraped_at": "2026-05-14T19:05:54.047Z"
  },
  {
    "instagram_handle": "@kenza.siba",
    "twitter_handle": null,
    "nom": "𝑲𝒆𝒏𝒛𝒂.siba",
    "bio": "Cavalière Je t’emmène dans mon quotidien équestre Équitation • Vlogs • Beauty 📩 Contact pro : kenzasiba.pro@gmail.com",
    "ville": "Paris",
    "abonnes_instagram": null,
    "abonnes_affiche": null,
    "secteur": "estheticienne",
    "email_contact": "kenzasiba.pro@gmail.com",
    "tarif_estime": "gratuit/produit",
    "statut": "à_contacter",
    "dans_cible": null,
    "source": "modash",
    "date_contact": null,
    "scraped_at": "2026-05-14T19:05:54.047Z"
  },
  {
    "instagram_handle": "@mohamedcheikh_",
    "twitter_handle": null,
    "nom": "Mohamed Cheikh | محمد شيخ",
    "bio": "🏆 TopChef Winner 2021 🇫🇷 🍽️ Restaurants @meida.so | @meatpacksteakhouse 🌯 Street Food @elcheikh.paris | @chikchill_fr 📧 Contact@elcheikhculinary.fr",
    "ville": "Paris",
    "abonnes_instagram": 461500,
    "abonnes_affiche": "461.5k",
    "secteur": "restaurant",
    "email_contact": "contact@elcheikhculinary.fr",
    "tarif_estime": "300-600€",
    "statut": "à_contacter",
    "dans_cible": false,
    "source": "modash",
    "date_contact": null,
    "scraped_at": "2026-05-14T19:05:54.046Z"
  },
  {
    "instagram_handle": "@jessetmilan",
    "twitter_handle": null,
    "nom": "Jess & Milan - Travel and Food Couple",
    "bio": "Un couple qui partage ce qu’il aime 🤍 Baby Girl is here ✨ 📍 à Paris / 520k TikTok collab@jessetmilan.com by @adcrew_agency 🤳🏼 jessetmilansursnap",
    "ville": "Paris",
    "abonnes_instagram": null,
    "abonnes_affiche": null,
    "secteur": "restaurant",
    "email_contact": "collab@jessetmilan.com",
    "tarif_estime": "gratuit/produit",
    "statut": "à_contacter",
    "dans_cible": null,
    "source": "modash",
    "date_contact": null,
    "scraped_at": "2026-05-14T19:05:54.046Z"
  },
  {
    "instagram_handle": "@kenousdiary",
    "twitter_handle": null,
    "nom": "Kenza Tham",
    "bio": "food & looots of gym influence manager..and more 📍franco-libanaise du Sénégal à Paris 💌kenousdiary@gmail.com",
    "ville": "Paris",
    "abonnes_instagram": null,
    "abonnes_affiche": null,
    "secteur": "restaurant",
    "email_contact": "kenousdiary@gmail.com",
    "tarif_estime": "gratuit/produit",
    "statut": "à_contacter",
    "dans_cible": null,
    "source": "modash",
    "date_contact": null,
    "scraped_at": "2026-05-14T19:05:54.046Z"
  },
  {
    "instagram_handle": "@foodalix",
    "twitter_handle": null,
    "nom": "Food Alix 🥑",
    "bio": "By @alix.grousset #FoodAlix @encuisineavecgrousset 📩 grousset.alix@gmail.com MON LIVRE ⬇️",
    "ville": "Paris",
    "abonnes_instagram": null,
    "abonnes_affiche": null,
    "secteur": "restaurant",
    "email_contact": "grousset.alix@gmail.com",
    "tarif_estime": "gratuit/produit",
    "statut": "à_contacter",
    "dans_cible": null,
    "source": "modash",
    "date_contact": null,
    "scraped_at": "2026-05-14T19:05:54.046Z"
  },
  {
    "instagram_handle": "@camillegrandxo",
    "twitter_handle": null,
    "nom": "Camille Grand",
    "bio": "Mode plus responsable, travel, food & angry music🤘 📍 Paris, made in 🇫🇷🇸🇬 💻 YouTube (125K) 🎤 CamilleGrandMusic (12K) 💌 camillegrandxo@gmail.com",
    "ville": "Paris",
    "abonnes_instagram": null,
    "abonnes_affiche": null,
    "secteur": "restaurant",
    "email_contact": "camillegrandxo@gmail.com",
    "tarif_estime": "gratuit/produit",
    "statut": "à_contacter",
    "dans_cible": null,
    "source": "modash",
    "date_contact": null,
    "scraped_at": "2026-05-14T19:05:54.046Z"
  },
  {
    "instagram_handle": "@paname_in_my_belly",
    "twitter_handle": null,
    "nom": "Paname in My Belly|Food Guide😋",
    "bio": "🙋🏻‍♂️Nathanaël aka Nathy le Glouton - Content Creator ⭐️Le guide des gloutons Parisiens + 🌍🥇 📩Collab: pimb.paris@gmail.com-DM Retrouve moi partout👇",
    "ville": "Paris",
    "abonnes_instagram": null,
    "abonnes_affiche": null,
    "secteur": "restaurant",
    "email_contact": "pimb.paris@gmail.com",
    "tarif_estime": "gratuit/produit",
    "statut": "à_contacter",
    "dans_cible": null,
    "source": "modash",
    "date_contact": null,
    "scraped_at": "2026-05-14T19:05:54.047Z"
  },
  {
    "instagram_handle": "@kinette_beautyfood",
    "twitter_handle": null,
    "nom": "Kinette Beautyfood",
    "bio": "📍𝔽𝕣𝕒𝕟𝕔𝕖 🇫🇷 𝔽𝕠𝕠𝕕 𝕃𝕠𝕧𝕖𝕣 🤍 ℝ𝕖𝕔𝕖𝕥𝕥𝕖𝕤 ✨ 🍰🥯 Collab : kinettebeautyfood@gmail.com",
    "ville": "Paris",
    "abonnes_instagram": 436900,
    "abonnes_affiche": "436.9k",
    "secteur": "restaurant",
    "email_contact": "kinettebeautyfood@gmail.com",
    "tarif_estime": "300-600€",
    "statut": "à_contacter",
    "dans_cible": false,
    "source": "modash",
    "date_contact": null,
    "scraped_at": "2026-05-14T19:05:54.047Z"
  },
  {
    "instagram_handle": "@julieferrat",
    "twitter_handle": null,
    "nom": "Julie 🌞",
    "bio": "le sunshine de votre life 🌞🌼🥭 🌊 lifestyle • 🏃‍♀️ sport • 🍳 food 💌 : julie@foll-ow.com Paris, Bordeaux 📍 ⬇️ le reste se passe ici",
    "ville": "Paris",
    "abonnes_instagram": null,
    "abonnes_affiche": null,
    "secteur": "restaurant",
    "email_contact": "julie@foll-ow.com",
    "tarif_estime": "gratuit/produit",
    "statut": "à_contacter",
    "dans_cible": null,
    "source": "modash",
    "date_contact": null,
    "scraped_at": "2026-05-14T19:05:54.047Z"
  },
  {
    "instagram_handle": "@lindoush_food",
    "twitter_handle": null,
    "nom": "Lindoush 👩‍🍳✨",
    "bio": "Il était une fois une recette.. ✨👩‍🍳 Vous aimez la food et les histoires ? 🍰 Alors bienvenue sur mon compte ! 🤗💞 💌 linda@futures.social",
    "ville": "Paris",
    "abonnes_instagram": null,
    "abonnes_affiche": null,
    "secteur": "restaurant",
    "email_contact": "linda@futures.social",
    "tarif_estime": "gratuit/produit",
    "statut": "à_contacter",
    "dans_cible": null,
    "source": "modash",
    "date_contact": null,
    "scraped_at": "2026-05-14T19:05:54.047Z"
  },
  {
    "instagram_handle": "@gracy_barberane",
    "twitter_handle": null,
    "nom": "Gracy Barberane",
    "bio": "📧 gracy@agencemadein.fr 💍 @fab_life_adventure Mum d’ado et de 🐶🐶🐈 Mum to be sept 2026 🤰🏻 PMA warrior 💪🏼 Travel, Food & Shopping therapy 🤍 📍Var",
    "ville": "Paris",
    "abonnes_instagram": 375700,
    "abonnes_affiche": "375.7k",
    "secteur": "restaurant",
    "email_contact": "gracy@agencemadein.fr",
    "tarif_estime": "300-600€",
    "statut": "à_contacter",
    "dans_cible": false,
    "source": "modash",
    "date_contact": null,
    "scraped_at": "2026-05-14T19:05:54.047Z"
  },
  {
    "instagram_handle": "@blondiemamaaa",
    "twitter_handle": null,
    "nom": "Marie-Caroline Cail",
    "bio": "☀️Marie-Ca | Maman x 6 🌈 📍Lyon Aventures familiales •Look • Food • Running 📧 blondiemamaaa@agencemadein.fr 👇🏼",
    "ville": "Lyon",
    "abonnes_instagram": 154500,
    "abonnes_affiche": "154.5k",
    "secteur": "restaurant",
    "email_contact": "blondiemamaaa@agencemadein.fr",
    "tarif_estime": "300-600€",
    "statut": "à_contacter",
    "dans_cible": false,
    "source": "modash",
    "date_contact": null,
    "scraped_at": "2026-05-14T19:05:54.047Z"
  },
  {
    "instagram_handle": "@loulouuutte",
    "twitter_handle": null,
    "nom": "Léa Weber 🦋",
    "bio": "📍entre Lille et Paris Mode | Lifestyle | Food | Travel 1m67 d’étourderies ⚡️Positive vibes 🌈 💌 loulouuuttepro@gmail.com",
    "ville": "Paris",
    "abonnes_instagram": 147400,
    "abonnes_affiche": "147.4k",
    "secteur": "restaurant",
    "email_contact": "loulouuuttepro@gmail.com",
    "tarif_estime": "300-600€",
    "statut": "à_contacter",
    "dans_cible": false,
    "source": "modash",
    "date_contact": null,
    "scraped_at": "2026-05-14T19:05:54.047Z"
  },
  {
    "instagram_handle": "@karenn_life",
    "twitter_handle": null,
    "nom": "ᴋᴀʀᴇɴ 🌺-𝓉𝑒𝒶𝒸𝒽𝑒𝓇,𝒻𝑜𝑜𝒹/𝒞𝓇𝑜𝓈𝓈𝐹𝒾𝓉",
    "bio": "Mum of Olivia👩🏼‍🍼Food, Lifestyle & Sport Collabs💌 karennlife@outlook.fr @nutripurefr 🇫🇷-10% KAREN @holysquad.fr -10% KAREN @braineffect_fr -20% KAREN",
    "ville": "Paris",
    "abonnes_instagram": 107000,
    "abonnes_affiche": "107.0k",
    "secteur": "restaurant",
    "email_contact": "karennlife@outlook.fr",
    "tarif_estime": "300-600€",
    "statut": "à_contacter",
    "dans_cible": false,
    "source": "modash",
    "date_contact": null,
    "scraped_at": "2026-05-14T19:05:54.047Z"
  },
  {
    "instagram_handle": "@lesrecettesdalexandra",
    "twitter_handle": null,
    "nom": "Alexandra BERNARD",
    "bio": "Good food Good mood ☀️ 🍓| Recettes healthy 🥑 🍰| Et plus gourmandes 🤭 💌 recettesdalexandra@gmail.com",
    "ville": "Paris",
    "abonnes_instagram": 93700,
    "abonnes_affiche": "93.7k",
    "secteur": "restaurant",
    "email_contact": "recettesdalexandra@gmail.com",
    "tarif_estime": "300-600€",
    "statut": "à_contacter",
    "dans_cible": false,
    "source": "modash",
    "date_contact": null,
    "scraped_at": "2026-05-14T19:05:54.047Z"
  },
  {
    "instagram_handle": "@dymanpasplus",
    "twitter_handle": null,
    "nom": "Mandy",
    "bio": "Une juriste devenue tiktokeuse🤓 FOOD & TRAVEL🍕✈️ Tous mes vlogs sur Tiktok&YouTube🎉 Tiktok : dymanpasplus (558k) 💌Pro : dymanpasplus.collab@gmail.com",
    "ville": "Paris",
    "abonnes_instagram": null,
    "abonnes_affiche": null,
    "secteur": "restaurant",
    "email_contact": "dymanpasplus.collab@gmail.com",
    "tarif_estime": "gratuit/produit",
    "statut": "à_contacter",
    "dans_cible": null,
    "source": "modash",
    "date_contact": null,
    "scraped_at": "2026-05-14T19:05:54.047Z"
  },
  {
    "instagram_handle": "@adelinerbr",
    "twitter_handle": null,
    "nom": "Adeline Ribeiro",
    "bio": "Paris, France fashion, travel & lifestyle home @casa_joline adelinerbr.pro@gmail.com",
    "ville": "Paris",
    "abonnes_instagram": null,
    "abonnes_affiche": null,
    "secteur": "salon_coiffure",
    "email_contact": "adelinerbr.pro@gmail.com",
    "tarif_estime": "gratuit/produit",
    "statut": "à_contacter",
    "dans_cible": null,
    "source": "modash",
    "date_contact": null,
    "scraped_at": "2026-05-14T19:05:54.046Z"
  },
  {
    "instagram_handle": "@marine_audineau",
    "twitter_handle": null,
    "nom": "Marine",
    "bio": "Paris lifestyle, fashion & travel triathlon training / Run’nine Club architect @the.moodernists 💌 audineaumarinepro@gmail.com",
    "ville": "Paris",
    "abonnes_instagram": 123000,
    "abonnes_affiche": "123.0k",
    "secteur": "salon_coiffure",
    "email_contact": "audineaumarinepro@gmail.com",
    "tarif_estime": "300-600€",
    "statut": "à_contacter",
    "dans_cible": false,
    "source": "modash",
    "date_contact": null,
    "scraped_at": "2026-05-14T19:05:54.047Z"
  },
  {
    "instagram_handle": "@amaltahir",
    "twitter_handle": null,
    "nom": "amaltahir",
    "bio": "Writer & Host of Garce Therapy 🎧 Modern romance, iconic bags and life under the Eiffel Tower contact@amaltahir.com 💋 @papier.stiletto",
    "ville": "Paris",
    "abonnes_instagram": 114700,
    "abonnes_affiche": "114.7k",
    "secteur": "salon_coiffure",
    "email_contact": "contact@amaltahir.com",
    "tarif_estime": "300-600€",
    "statut": "à_contacter",
    "dans_cible": false,
    "source": "modash",
    "date_contact": null,
    "scraped_at": "2026-05-14T19:05:54.047Z"
  },
  {
    "instagram_handle": "@laugh_of_artist",
    "twitter_handle": null,
    "nom": "Victoria Gasperi",
    "bio": "Fashion • Spirituality • Paris ☾ Host Podcast ‘Rue des Dames’🎙️ contact@laugh-of-artist.com",
    "ville": "Paris",
    "abonnes_instagram": 109800,
    "abonnes_affiche": "109.8k",
    "secteur": "salon_coiffure",
    "email_contact": "contact@laugh-of-artist.com",
    "tarif_estime": "300-600€",
    "statut": "à_contacter",
    "dans_cible": false,
    "source": "modash",
    "date_contact": null,
    "scraped_at": "2026-05-14T19:05:54.047Z"
  },
  {
    "instagram_handle": "@pretemoitaveste",
    "twitter_handle": null,
    "nom": "Marine",
    "bio": "Fashion & Interior Half of @nouslanuit 📍PARIS ✉️ pretemoitaveste@gmail.com",
    "ville": "Paris",
    "abonnes_instagram": null,
    "abonnes_affiche": null,
    "secteur": "salon_coiffure",
    "email_contact": "pretemoitaveste@gmail.com",
    "tarif_estime": "gratuit/produit",
    "statut": "à_contacter",
    "dans_cible": null,
    "source": "modash",
    "date_contact": null,
    "scraped_at": "2026-05-14T19:05:54.047Z"
  },
  {
    "instagram_handle": "@marine_breadwhite",
    "twitter_handle": null,
    "nom": "Marine Breadwhite 🌈",
    "bio": "📸 Free-lance Product Content Creator - UGC ☀️Fashion -Lifestyle- Travel ✉️ marine.breadwhite@gmail.com 📍PARIS - HOSSEGOR",
    "ville": "Paris",
    "abonnes_instagram": 95300,
    "abonnes_affiche": "95.3k",
    "secteur": "salon_coiffure",
    "email_contact": "marine.breadwhite@gmail.com",
    "tarif_estime": "300-600€",
    "statut": "à_contacter",
    "dans_cible": false,
    "source": "modash",
    "date_contact": null,
    "scraped_at": "2026-05-14T19:05:54.047Z"
  },
  {
    "instagram_handle": "@elijx",
    "twitter_handle": null,
    "nom": "élise,",
    "bio": "paris, vegetarian 25yo 🍓✨ @eljead_studio fashion designer/stylist who loves prints, colors, mangas and second hand shops✨ contact@elijx.com",
    "ville": "Paris",
    "abonnes_instagram": 83200,
    "abonnes_affiche": "83.2k",
    "secteur": "salon_coiffure",
    "email_contact": "contact@elijx.com",
    "tarif_estime": "300-600€",
    "statut": "à_contacter",
    "dans_cible": false,
    "source": "modash",
    "date_contact": null,
    "scraped_at": "2026-05-14T19:05:54.047Z"
  },
  {
    "instagram_handle": "@juliettepuy",
    "twitter_handle": null,
    "nom": "Juliette",
    "bio": "Paris, France minimal fashion, makeup & travel jjjulietpuy@gmail.com",
    "ville": "Paris",
    "abonnes_instagram": null,
    "abonnes_affiche": null,
    "secteur": "salon_coiffure",
    "email_contact": "jjjulietpuy@gmail.com",
    "tarif_estime": "gratuit/produit",
    "statut": "à_contacter",
    "dans_cible": null,
    "source": "modash",
    "date_contact": null,
    "scraped_at": "2026-05-14T19:05:54.047Z"
  },
  {
    "instagram_handle": "@eurasianfr_",
    "twitter_handle": null,
    "nom": "TIPHAINE - N A L A LINH 🐲 ✨",
    "bio": "• French & Vietnamese 🇫🇷x🇻🇳 • 💌 Colab/work : nala.creator.ugc@gmail.com • Fitness | lifestyle | wellness",
    "ville": "Paris",
    "abonnes_instagram": 7000,
    "abonnes_affiche": "7.0k",
    "secteur": "spa",
    "email_contact": "nala.creator.ugc@gmail.com",
    "tarif_estime": "gratuit/produit",
    "statut": "à_contacter",
    "dans_cible": false,
    "source": "modash",
    "date_contact": null,
    "scraped_at": "2026-05-14T19:05:54.047Z"
  },
  {
    "instagram_handle": "@telma.gymsis",
    "twitter_handle": null,
    "nom": "Telma | Coach fitness 🎀",
    "bio": "Personal trainer and booty builder | Paris @womensbest team | ‘TELMA’ 💌 fit.telma@gmail.com ⬇️ demande de coaching ⬇️",
    "ville": "Paris",
    "abonnes_instagram": 6500,
    "abonnes_affiche": "6.5k",
    "secteur": "spa",
    "email_contact": "fit.telma@gmail.com",
    "tarif_estime": "gratuit/produit",
    "statut": "à_contacter",
    "dans_cible": false,
    "source": "modash",
    "date_contact": null,
    "scraped_at": "2026-05-14T19:05:54.047Z"
  },
  {
    "instagram_handle": "@jonathandjr_",
    "twitter_handle": null,
    "nom": "Jonathan",
    "bio": "Lifestyle • Fitness • Travel 🌍 35 countries 📩 jonathandjerehe@gmail.com",
    "ville": "Paris",
    "abonnes_instagram": null,
    "abonnes_affiche": null,
    "secteur": "spa",
    "email_contact": "jonathandjerehe@gmail.com",
    "tarif_estime": "gratuit/produit",
    "statut": "à_contacter",
    "dans_cible": null,
    "source": "modash",
    "date_contact": null,
    "scraped_at": "2026-05-14T19:05:54.047Z"
  },
  {
    "instagram_handle": "@yoann.russel",
    "twitter_handle": null,
    "nom": "RUSSEL",
    "bio": "▫️Préparateur physique / Accompagnement sportif et alimentation. ▫️Ambassadeur fitness @roc_nutrition 🤝 🖊️Contact pro 📧 yoprodigital@hotmail.com",
    "ville": "Paris",
    "abonnes_instagram": 80700,
    "abonnes_affiche": "80.7k",
    "secteur": "spa",
    "email_contact": "yoprodigital@hotmail.com",
    "tarif_estime": "300-600€",
    "statut": "à_contacter",
    "dans_cible": false,
    "source": "modash",
    "date_contact": null,
    "scraped_at": "2026-05-14T19:05:54.047Z"
  },
  {
    "instagram_handle": "@alichuree",
    "twitter_handle": null,
    "nom": "Alicia Martinez",
    "bio": "chantent nos feeds avec leurs idées et leur flair artistique. Alicia Martinez Alicia Martinez, connue sous le pseudo alichuree , est l’une des influenceurs décoration incontournables sur les réseaux s",
    "ville": "Paris",
    "abonnes_instagram": 797000,
    "abonnes_affiche": "797.0k",
    "secteur": "architecte_interieur",
    "email_contact": null,
    "tarif_estime": "300-600€",
    "statut": "ig_trouvé",
    "dans_cible": false,
    "source": "ranking_page",
    "date_contact": null,
    "scraped_at": "2026-05-14T19:05:54.047Z"
  },
  {
    "instagram_handle": "@legrenierdetom",
    "twitter_handle": null,
    "nom": "Tom - Déco Coiffure Lifestyle DIY",
    "bio": "ée par Alicia Martinez (@alichuree) Le grenier de Tom Tom, plus connu sous le nom de legrenierdetom sur les réseaux sociaux, fait partie des influenceurs décoration en vogue. Avec une présence remarqu",
    "ville": "Paris",
    "abonnes_instagram": null,
    "abonnes_affiche": null,
    "secteur": "architecte_interieur",
    "email_contact": null,
    "tarif_estime": "gratuit/produit",
    "statut": "ig_trouvé",
    "dans_cible": null,
    "source": "ranking_page",
    "date_contact": null,
    "scraped_at": "2026-05-14T19:05:54.047Z"
  },
  {
    "instagram_handle": "@rachelstyliste",
    "twitter_handle": null,
    "nom": "Rachel Styliste mode & deco",
    "bio": "| 𝙲𝚘𝚒𝚏𝚏𝚞𝚛𝚎 | 𝙻𝚒𝚏𝚎𝚜𝚝𝚢𝚕𝚎 | 𝙳𝚒𝚢 🍂 (@legrenierdetom) Rachel Styliste Rachel Styliste brille sur Instagram avec son feed épuré et ses tons doux qui captivent instantanément. Son mantra",
    "ville": "Paris",
    "abonnes_instagram": null,
    "abonnes_affiche": null,
    "secteur": "architecte_interieur",
    "email_contact": null,
    "tarif_estime": "gratuit/produit",
    "statut": "ig_trouvé",
    "dans_cible": null,
    "source": "ranking_page",
    "date_contact": null,
    "scraped_at": "2026-05-14T19:05:54.047Z"
  },
  {
    "instagram_handle": "@romaincosta_",
    "twitter_handle": null,
    "nom": "Romain Costa",
    "bio": "achel Styliste mode &amp; deco (@rachelstyliste) Romain Costa Natif du nord de la France, Romain Costa est aujourd’hui propriétaire d’un cabinet d’architecture florissant à Paris. Son mantra, «&nbsp; ",
    "ville": "Paris",
    "abonnes_instagram": null,
    "abonnes_affiche": null,
    "secteur": "architecte_interieur",
    "email_contact": null,
    "tarif_estime": "gratuit/produit",
    "statut": "ig_trouvé",
    "dans_cible": null,
    "source": "ranking_page",
    "date_contact": null,
    "scraped_at": "2026-05-14T19:05:54.047Z"
  },
  {
    "instagram_handle": "@joannagaines",
    "twitter_handle": null,
    "nom": null,
    "bio": "sta_) Joanna Gaines Avec près de 13,8 millions d’abonnés sur Instagram , Joanna Gaines est une influenceuse de renom.&nbsp; Artiste et architecte d’intérieur, elle forme avec son mari Chip un duo de",
    "ville": "Paris",
    "abonnes_instagram": 13800000,
    "abonnes_affiche": "13.8M",
    "secteur": "architecte_interieur",
    "email_contact": null,
    "tarif_estime": "300-600€",
    "statut": "ig_trouvé",
    "dans_cible": false,
    "source": "ranking_page",
    "date_contact": null,
    "scraped_at": "2026-05-14T19:05:54.047Z"
  },
  {
    "instagram_handle": "@rivassouxemmanuelle",
    "twitter_handle": null,
    "nom": null,
    "bio": "\">Une publication partagée par Joanna Gaines (@joannagaines) Emmanuelle Rivassoux Emmanuelle Rivassoux , architecte d’intérieur renommée, rayonne principalement sur Instagram avec une communauté de 37",
    "ville": "Paris",
    "abonnes_instagram": 373000,
    "abonnes_affiche": "373.0k",
    "secteur": "architecte_interieur",
    "email_contact": null,
    "tarif_estime": "300-600€",
    "statut": "ig_trouvé",
    "dans_cible": false,
    "source": "ranking_page",
    "date_contact": null,
    "scraped_at": "2026-05-14T19:05:54.047Z"
  },
  {
    "instagram_handle": "@idoitmyself.be",
    "twitter_handle": null,
    "nom": null,
    "bio": "Emmanuelle RIVASSOUX (@rivassouxemmanuelle) Céline Thiteux Céline Thiteux, alias «&nbsp; idoitmyself.be &nbsp;» sur Instagram, rassemble une communauté de 240 000 fidèles sur cette plateforme.&nbsp; S",
    "ville": "Paris",
    "abonnes_instagram": null,
    "abonnes_affiche": null,
    "secteur": "architecte_interieur",
    "email_contact": null,
    "tarif_estime": "gratuit/produit",
    "statut": "ig_trouvé",
    "dans_cible": null,
    "source": "ranking_page",
    "date_contact": null,
    "scraped_at": "2026-05-14T19:05:54.047Z"
  },
  {
    "instagram_handle": "@metricool.fr",
    "twitter_handle": null,
    "nom": null,
    "bio": "PSIjZmZmZmZmIi8+PC9zdmc+\" data-src=\"https://metricool.com/wp-content/uploads/fb-icon-footer.svg\" alt=\"Facebook\" width=\"32\" height=\"32\" style=\"object-fit: contain;\"> <img data-lazyloaded=\"1\" src=\"data:",
    "ville": "Paris",
    "abonnes_instagram": 53000000,
    "abonnes_affiche": "53.0M",
    "secteur": "architecte_interieur",
    "email_contact": null,
    "tarif_estime": "300-600€",
    "statut": "ig_trouvé",
    "dans_cible": false,
    "source": "ranking_page",
    "date_contact": null,
    "scraped_at": "2026-05-14T19:05:54.047Z"
  },
  {
    "instagram_handle": "@this_perfectday",
    "twitter_handle": null,
    "nom": "Béné 🥳",
    "bio": "😎 Denise, Influenceuse en carton 🫶🏼 PhD en maman parfaitement imparfaite, bouclettes et Skincare 😁: Faut regoler ! 👸🏼 Impossible n’est pas féminin !",
    "ville": "Paris",
    "abonnes_instagram": 101500,
    "abonnes_affiche": "101.5k",
    "secteur": "clinique_esthetique",
    "email_contact": null,
    "tarif_estime": "300-600€",
    "statut": "ig_trouvé",
    "dans_cible": false,
    "source": "modash",
    "date_contact": null,
    "scraped_at": "2026-05-14T19:05:54.047Z"
  },
  {
    "instagram_handle": "@ambre_tbg",
    "twitter_handle": null,
    "nom": "Ambre Trecy",
    "bio": "Plus Size Fashion, beauty and lifestyle Ambre & Farida on YT ( +110k) Snap: ambretrecy Paris 📍",
    "ville": "Paris",
    "abonnes_instagram": null,
    "abonnes_affiche": null,
    "secteur": "estheticienne",
    "email_contact": null,
    "tarif_estime": "gratuit/produit",
    "statut": "ig_trouvé",
    "dans_cible": null,
    "source": "modash",
    "date_contact": null,
    "scraped_at": "2026-05-14T19:05:54.046Z"
  },
  {
    "instagram_handle": "@rasta_do10",
    "twitter_handle": null,
    "nom": "💋Dodo💋",
    "bio": "•Lifestyle | Beauty | Mode 💄 •Good Vibes ✨❤️‍🔥🥰 •👻: doriane97320",
    "ville": "Paris",
    "abonnes_instagram": null,
    "abonnes_affiche": null,
    "secteur": "estheticienne",
    "email_contact": null,
    "tarif_estime": "gratuit/produit",
    "statut": "ig_trouvé",
    "dans_cible": null,
    "source": "modash",
    "date_contact": null,
    "scraped_at": "2026-05-14T19:05:54.047Z"
  },
  {
    "instagram_handle": "@inparisalice",
    "twitter_handle": null,
    "nom": "Alice",
    "bio": "Mes vacances à @chamonixmontblanc ❄️ https://youtu.be/TVp5ZJWEakI 📍 Currently in Paris Travel ✈️ Food 🥗🥑 Beauty 💄 Lifestyle 💁🏻‍♀️",
    "ville": "Paris",
    "abonnes_instagram": 91000,
    "abonnes_affiche": "91.0k",
    "secteur": "estheticienne",
    "email_contact": null,
    "tarif_estime": "300-600€",
    "statut": "ig_trouvé",
    "dans_cible": false,
    "source": "modash",
    "date_contact": null,
    "scraped_at": "2026-05-14T19:05:54.047Z"
  },
  {
    "instagram_handle": "@ne",
    "twitter_handle": null,
    "nom": "Microphone",
    "bio": "Microphone Rode Micro pour Smartphone Videomic ME-C 5/5 (1 avis) Les points forts Conçu pour les appareils mobiles dotés d'une entrée USB-C (y compris les appareils Android et iOS) Prise de sortie …",
    "ville": "Paris",
    "abonnes_instagram": 9000000,
    "abonnes_affiche": "9.0M",
    "secteur": "estheticienne",
    "email_contact": null,
    "tarif_estime": "300-600€",
    "statut": "ig_trouvé",
    "dans_cible": false,
    "source": "bing",
    "date_contact": null,
    "scraped_at": "2026-05-14T19:05:54.047Z"
  },
  {
    "instagram_handle": "@lenamahfouf",
    "twitter_handle": null,
    "nom": null,
    "bio": "e: 24px; color: #000000;\">Le top 10 des influenceurs beauté instagram en France &nbsp; 1. Lena Situations • @lenamahfouf &nbsp; Lena Situations, de son vrai nom Lena Mahfouf, est une véritable icône I",
    "ville": "France",
    "abonnes_instagram": null,
    "abonnes_affiche": null,
    "secteur": "estheticienne",
    "email_contact": null,
    "tarif_estime": "gratuit/produit",
    "statut": "ig_trouvé",
    "dans_cible": null,
    "source": "ranking_page",
    "date_contact": null,
    "scraped_at": "2026-05-14T19:05:54.047Z"
  },
  {
    "instagram_handle": "@sananas2106",
    "twitter_handle": null,
    "nom": null,
    "bio": "r%C3%A9ateurs%20mentionn%C3%A9es%20par%20les%20influenceurs.jpg 2049w\" sizes=\"(max-width: 683px) 100vw, 683px\"> &nbsp; 2. Sananas • @sananas2106 &nbsp; Sananas, de son vrai nom Sanaa El Mahalli, est u",
    "ville": "France",
    "abonnes_instagram": 20000000,
    "abonnes_affiche": "20.0M",
    "secteur": "estheticienne",
    "email_contact": null,
    "tarif_estime": "300-600€",
    "statut": "ig_trouvé",
    "dans_cible": false,
    "source": "ranking_page",
    "date_contact": null,
    "scraped_at": "2026-05-14T19:05:54.047Z"
  },
  {
    "instagram_handle": "@paolalct",
    "twitter_handle": null,
    "nom": null,
    "bio": "an>sananas2106 👍2.7&nbsp;millions de followers 💬 0.35% d’engagement moyen sur Instagram &nbsp; 3. Paola Locatelli • @paolalct &nbsp; Paola Locatelli, jeune influenceuse française, s'est rapidement i",
    "ville": "Paris",
    "abonnes_instagram": 1900000,
    "abonnes_affiche": "1.9M",
    "secteur": "estheticienne",
    "email_contact": null,
    "tarif_estime": "300-600€",
    "statut": "ig_trouvé",
    "dans_cible": false,
    "source": "ranking_page",
    "date_contact": null,
    "scraped_at": "2026-05-14T19:05:54.047Z"
  },
  {
    "instagram_handle": "@romy",
    "twitter_handle": null,
    "nom": null,
    "bio": "l=\"noopener\" target=\"_blank\">Top 10 des meilleurs influenceurs TikTok en France en 2023 &nbsp; &nbsp; 4. Romane, pour les intimes • @romy &nbsp; Romy , connue pour son élégance naturelle et son style ",
    "ville": "France",
    "abonnes_instagram": 1510000,
    "abonnes_affiche": "1.5M",
    "secteur": "estheticienne",
    "email_contact": null,
    "tarif_estime": "300-600€",
    "statut": "ig_trouvé",
    "dans_cible": false,
    "source": "ranking_page",
    "date_contact": null,
    "scraped_at": "2026-05-14T19:05:54.047Z"
  },
  {
    "instagram_handle": "@yanissaxoxo",
    "twitter_handle": null,
    "nom": null,
    "bio": "span> &nbsp; 👍 1.51 million&nbsp;de followers sur Instagram 💬 1.37% d’engagement moyen sur Instagram &nbsp; 5. Yanissa 💖 • @yanissaxoxo &nbsp; Yanissa est une influenceuse instagram dynamique et ch",
    "ville": "Paris",
    "abonnes_instagram": 1510000,
    "abonnes_affiche": "1.5M",
    "secteur": "estheticienne",
    "email_contact": null,
    "tarif_estime": "300-600€",
    "statut": "ig_trouvé",
    "dans_cible": false,
    "source": "ranking_page",
    "date_contact": null,
    "scraped_at": "2026-05-14T19:05:54.047Z"
  },
  {
    "instagram_handle": "@my_origines",
    "twitter_handle": null,
    "nom": null,
    "bio": "avec des marques telles que Nyx , Sephora , MyOrigines ou BananaBeauty sont souvent innovantes et en phase avec les tendances beauté actuelles , ce qui en fait une source d'inspiration inconto",
    "ville": "Paris",
    "abonnes_instagram": null,
    "abonnes_affiche": null,
    "secteur": "estheticienne",
    "email_contact": null,
    "tarif_estime": "gratuit/produit",
    "statut": "ig_trouvé",
    "dans_cible": null,
    "source": "ranking_page",
    "date_contact": null,
    "scraped_at": "2026-05-14T19:05:54.047Z"
  },
  {
    "instagram_handle": "@lufyyyy",
    "twitter_handle": null,
    "nom": null,
    "bio": ": Top 10 des influenceurs Luxe en France 6. ​​L U F Y 🖤 • @lufyyyy &nbsp; L U F Y, alias Lucie Fink, est une influenceuse belge reconnue pour son approche authentique et inspirante de la beauté .&nbs",
    "ville": "France",
    "abonnes_instagram": 1200000,
    "abonnes_affiche": "1.2M",
    "secteur": "estheticienne",
    "email_contact": null,
    "tarif_estime": "300-600€",
    "statut": "ig_trouvé",
    "dans_cible": false,
    "source": "ranking_page",
    "date_contact": null,
    "scraped_at": "2026-05-14T19:05:54.047Z"
  },
  {
    "instagram_handle": "@mayadorable",
    "twitter_handle": null,
    "nom": null,
    "bio": "ufyyyy &nbsp; 👍 1.2 million&nbsp;de followers sur Instagram 💬 1.9% d’engagement moyen sur Instagram 7. Maya🐝🐝🐝 • @mayadorable &nbsp; Maya est une influenceuse française reconnue pour son style un",
    "ville": "Paris",
    "abonnes_instagram": 1200000,
    "abonnes_affiche": "1.2M",
    "secteur": "estheticienne",
    "email_contact": null,
    "tarif_estime": "300-600€",
    "statut": "ig_trouvé",
    "dans_cible": false,
    "source": "ranking_page",
    "date_contact": null,
    "scraped_at": "2026-05-14T19:05:54.047Z"
  },
  {
    "instagram_handle": "@mayadesagreable",
    "twitter_handle": null,
    "nom": null,
    "bio": "d;\">tendances beauté contemporaines la rend particulièrement attrayante pour un public jeune et branché. &nbsp; Elle a développé avec humour un second compte @mayadesagreable où elle partage ses avent",
    "ville": "Paris",
    "abonnes_instagram": null,
    "abonnes_affiche": null,
    "secteur": "estheticienne",
    "email_contact": null,
    "tarif_estime": "gratuit/produit",
    "statut": "ig_trouvé",
    "dans_cible": null,
    "source": "ranking_page",
    "date_contact": null,
    "scraped_at": "2026-05-14T19:05:54.047Z"
  },
  {
    "instagram_handle": "@iammaevamartinez",
    "twitter_handle": null,
    "nom": null,
    "bio": "p>💬 3.1% d’engagement moyen sur Instagram 8. 𝙼𝙰𝙴𝚅𝙰 🪐 • @iammaevamartinez &nbsp; Maeva Martinez est une personnalité influente dans le monde de la beauté sur les réseaux sociaux &nbsp;💄</p",
    "ville": "Paris",
    "abonnes_instagram": 8000000,
    "abonnes_affiche": "8.0M",
    "secteur": "estheticienne",
    "email_contact": null,
    "tarif_estime": "300-600€",
    "statut": "ig_trouvé",
    "dans_cible": false,
    "source": "ranking_page",
    "date_contact": null,
    "scraped_at": "2026-05-14T19:05:54.047Z"
  },
  {
    "instagram_handle": "@chloebbbb",
    "twitter_handle": null,
    "nom": null,
    "bio": "r\" target=\"_blank\">Le Top des marques de crème solaire les plus citées par les influenceurs &nbsp; 9. Chloé Bleinc • @chloebbbb &nbsp; Chloé Bleinc, connue sous son pseudonyme Instagram @chloebbbb , ",
    "ville": "Paris",
    "abonnes_instagram": null,
    "abonnes_affiche": null,
    "secteur": "estheticienne",
    "email_contact": null,
    "tarif_estime": "gratuit/produit",
    "statut": "ig_trouvé",
    "dans_cible": null,
    "source": "ranking_page",
    "date_contact": null,
    "scraped_at": "2026-05-14T19:05:54.047Z"
  },
  {
    "instagram_handle": "@styleto",
    "twitter_handle": null,
    "nom": null,
    "bio": "> 👍 993&nbsp;000 followers sur Instagram 💬 1.8% d’engagement moyen sur Instagram 10. STYLETO • &nbsp; @styleto &nbsp; Laure, connue comme influenceuse sur Instagram sous le nom de @styleto , partage",
    "ville": "Paris",
    "abonnes_instagram": 795000,
    "abonnes_affiche": "795.0k",
    "secteur": "estheticienne",
    "email_contact": null,
    "tarif_estime": "300-600€",
    "statut": "ig_trouvé",
    "dans_cible": false,
    "source": "ranking_page",
    "date_contact": null,
    "scraped_at": "2026-05-14T19:05:54.047Z"
  },
  {
    "instagram_handle": "@lou.faitdesvideos",
    "twitter_handle": null,
    "nom": "Lou fait des vidéos✨",
    "bio": "✨ Food, Travel & Family 💕 🌍 Cuisine du monde, facile & gourmande ! ⬇️📚Notre livre : “On cuisine le monde en famille” 🧡⬇️",
    "ville": "Paris",
    "abonnes_instagram": 542300,
    "abonnes_affiche": "542.3k",
    "secteur": "restaurant",
    "email_contact": null,
    "tarif_estime": "300-600€",
    "statut": "ig_trouvé",
    "dans_cible": false,
    "source": "modash",
    "date_contact": null,
    "scraped_at": "2026-05-14T19:05:54.046Z"
  },
  {
    "instagram_handle": "@justunfrenchie",
    "twitter_handle": null,
    "nom": "Justin M | ☕ Healthy Food & Lifestyle",
    "bio": "🌿Créateur de bonnes choses & de good vibes 🌞| just’un frenchie qui partage sa ptite vie 🏃🏽| Sportif hyperactif / @on ambassador 🇫🇷| PARIS",
    "ville": "Paris",
    "abonnes_instagram": 174000,
    "abonnes_affiche": "174.0k",
    "secteur": "restaurant",
    "email_contact": null,
    "tarif_estime": "300-600€",
    "statut": "ig_trouvé",
    "dans_cible": false,
    "source": "modash",
    "date_contact": null,
    "scraped_at": "2026-05-14T19:05:54.046Z"
  },
  {
    "instagram_handle": "@alicemoireau",
    "twitter_handle": null,
    "nom": "Alice Moireau",
    "bio": "food life co-founder @t__a__b__l__e owner @lechaletolivet",
    "ville": "Paris",
    "abonnes_instagram": 122700,
    "abonnes_affiche": "122.7k",
    "secteur": "restaurant",
    "email_contact": null,
    "tarif_estime": "300-600€",
    "statut": "ig_trouvé",
    "dans_cible": false,
    "source": "modash",
    "date_contact": null,
    "scraped_at": "2026-05-14T19:05:54.046Z"
  },
  {
    "instagram_handle": "@leanvndtl",
    "twitter_handle": null,
    "nom": "Léanne",
    "bio": "pilates, lifestyle, healthy food & dog mum +848k on TikTok des recettes sans sucre & sans gluten en réels",
    "ville": "Paris",
    "abonnes_instagram": null,
    "abonnes_affiche": null,
    "secteur": "restaurant",
    "email_contact": null,
    "tarif_estime": "gratuit/produit",
    "statut": "ig_trouvé",
    "dans_cible": null,
    "source": "modash",
    "date_contact": null,
    "scraped_at": "2026-05-14T19:05:54.047Z"
  },
  {
    "instagram_handle": "@aurore.cookbooks",
    "twitter_handle": null,
    "nom": "Aurore | Recettes historiques",
    "bio": "🍇À la pointe des trends food !(du XIXe…) 🍳Je te fais goûter de délicieuses recettes 🗝️On voyage dans l’histoire 🌸Mon premier livre immersif :",
    "ville": "Paris",
    "abonnes_instagram": 142400,
    "abonnes_affiche": "142.4k",
    "secteur": "restaurant",
    "email_contact": null,
    "tarif_estime": "300-600€",
    "statut": "ig_trouvé",
    "dans_cible": false,
    "source": "modash",
    "date_contact": null,
    "scraped_at": "2026-05-14T19:05:54.047Z"
  },
  {
    "instagram_handle": "@linh.thuu",
    "twitter_handle": null,
    "nom": "Linh Thuu 🇻🇳",
    "bio": "✨ Influenceuse lifestyle | food | humour 💆🏻‍♀️ @linhatelier.nantes 📍Nantes",
    "ville": "Nantes",
    "abonnes_instagram": 83200,
    "abonnes_affiche": "83.2k",
    "secteur": "restaurant",
    "email_contact": null,
    "tarif_estime": "300-600€",
    "statut": "ig_trouvé",
    "dans_cible": false,
    "source": "modash",
    "date_contact": null,
    "scraped_at": "2026-05-14T19:05:54.047Z"
  },
  {
    "instagram_handle": "@simplicite_ici",
    "twitter_handle": null,
    "nom": "Simplicite_ici",
    "bio": "PARIS , Mom of 2 Fashion / Interior 💌 for collab",
    "ville": "Paris",
    "abonnes_instagram": 89100,
    "abonnes_affiche": "89.1k",
    "secteur": "salon_coiffure",
    "email_contact": null,
    "tarif_estime": "300-600€",
    "statut": "ig_trouvé",
    "dans_cible": false,
    "source": "modash",
    "date_contact": null,
    "scraped_at": "2026-05-14T19:05:54.047Z"
  },
  {
    "instagram_handle": "@mademoisellemodeuse",
    "twitter_handle": null,
    "nom": "Alexandra Fleurisson 🌼 Inspi mode, déco & voyage ✨",
    "bio": "🔥 Fashion girlie en taille 46✨ 🌍 Voyages & lifestyle pour une vie stylée ✍️ Créatrice digitale depuis 2012 | Entrepreneure 📸 📍Bordeaux / Paris",
    "ville": "Paris",
    "abonnes_instagram": 87200,
    "abonnes_affiche": "87.2k",
    "secteur": "salon_coiffure",
    "email_contact": null,
    "tarif_estime": "300-600€",
    "statut": "ig_trouvé",
    "dans_cible": false,
    "source": "modash",
    "date_contact": null,
    "scraped_at": "2026-05-14T19:05:54.047Z"
  },
  {
    "instagram_handle": "@lagirlmel_",
    "twitter_handle": null,
    "nom": "Mel",
    "bio": "Mes routines à 33 ans | 178cm 🌱✨ Lifestyle | Skincare @gymshark code LAGIRLMEL10 📍Paris",
    "ville": "Paris",
    "abonnes_instagram": null,
    "abonnes_affiche": null,
    "secteur": "spa",
    "email_contact": null,
    "tarif_estime": "gratuit/produit",
    "statut": "ig_trouvé",
    "dans_cible": null,
    "source": "modash",
    "date_contact": null,
    "scraped_at": "2026-05-14T19:05:54.047Z"
  },
  {
    "instagram_handle": "@thenarcissichealth",
    "twitter_handle": null,
    "nom": "COACH DOMI - ✨FITNESS • SELF LOVE • GROWTH ✨",
    "bio": "Ta copine coach, 👑Pour mes queen qui veulent enfin passer à l’action 🧪Experte pour ta technique et tes résultats 📍TCBOX :77 allée du forum 92100",
    "ville": "Paris",
    "abonnes_instagram": 81600,
    "abonnes_affiche": "81.6k",
    "secteur": "spa",
    "email_contact": null,
    "tarif_estime": "300-600€",
    "statut": "ig_trouvé",
    "dans_cible": false,
    "source": "modash",
    "date_contact": null,
    "scraped_at": "2026-05-14T19:05:54.047Z"
  },
  {
    "instagram_handle": "@jaymoves_",
    "twitter_handle": null,
    "nom": "jaymoves_",
    "bio": "PVRIS 📍🧃 Fitness | Pole Dancer | Performer |",
    "ville": "Paris",
    "abonnes_instagram": 6800,
    "abonnes_affiche": "6.8k",
    "secteur": "spa",
    "email_contact": null,
    "tarif_estime": "gratuit/produit",
    "statut": "ig_trouvé",
    "dans_cible": false,
    "source": "modash",
    "date_contact": null,
    "scraped_at": "2026-05-14T19:05:54.047Z"
  },
  {
    "instagram_handle": "@ptit_arno",
    "twitter_handle": null,
    "nom": "Arnaud",
    "bio": "Entrepreneur 🇫🇷 Real Estate 🏢 founder @ag_conseils_immo Design 🤍 owner @casa.citrus Fitness 💪🏻 Travel 🌍",
    "ville": "Paris",
    "abonnes_instagram": 6300,
    "abonnes_affiche": "6.3k",
    "secteur": "spa",
    "email_contact": null,
    "tarif_estime": "gratuit/produit",
    "statut": "ig_trouvé",
    "dans_cible": false,
    "source": "modash",
    "date_contact": null,
    "scraped_at": "2026-05-14T19:05:54.047Z"
  },
  {
    "instagram_handle": "@milkes2017",
    "twitter_handle": null,
    "nom": "Pol didier",
    "bio": "- French model Fitness. 🇫🇷 - Fitness lover 🏋️‍♀️. - To know how to love others, first learn to love yourself and respect yourself.",
    "ville": "Paris",
    "abonnes_instagram": 6100,
    "abonnes_affiche": "6.1k",
    "secteur": "spa",
    "email_contact": null,
    "tarif_estime": "gratuit/produit",
    "statut": "ig_trouvé",
    "dans_cible": false,
    "source": "modash",
    "date_contact": null,
    "scraped_at": "2026-05-14T19:05:54.047Z"
  },
  {
    "instagram_handle": "@killianloddo",
    "twitter_handle": null,
    "nom": "Killian Loddo",
    "bio": "█▀▀ █▀█ █▀█ █ █▄▄ █▄█ █▄█ █▄▄ 🍓🍇🍑 🍊Art director at @glgth / Personnal Trainer fitness instructor @killian_loddo_coaching - Paris",
    "ville": "Paris",
    "abonnes_instagram": 5200,
    "abonnes_affiche": "5.2k",
    "secteur": "spa",
    "email_contact": null,
    "tarif_estime": "gratuit/produit",
    "statut": "ig_trouvé",
    "dans_cible": false,
    "source": "modash",
    "date_contact": null,
    "scraped_at": "2026-05-14T19:05:54.047Z"
  },
  {
    "instagram_handle": "@margot_contri_coaching",
    "twitter_handle": null,
    "nom": "Coach sportif ☼ Pilates & Fitness",
    "bio": "Margot Gérante & coach chez @mb_studio_pilatesfitness Ma vie de #maman & de famille d'accueil Programme sur mesure créé par une femme pour les femmes",
    "ville": "Paris",
    "abonnes_instagram": 4900,
    "abonnes_affiche": "4.9k",
    "secteur": "spa",
    "email_contact": null,
    "tarif_estime": "gratuit/produit",
    "statut": "ig_trouvé",
    "dans_cible": false,
    "source": "modash",
    "date_contact": null,
    "scraped_at": "2026-05-14T19:05:54.047Z"
  },
  {
    "instagram_handle": "@claire_mli",
    "twitter_handle": null,
    "nom": "Claire Mli",
    "bio": "CEO of @impress_collecti0n57 ✨ ∂σи'т вє αfяαι∂ тσ вє уσυ ✨ ✨ ιи fαѕнισи ι тяυѕт ✨",
    "ville": "Paris",
    "abonnes_instagram": 4900,
    "abonnes_affiche": "4.9k",
    "secteur": "spa",
    "email_contact": null,
    "tarif_estime": "gratuit/produit",
    "statut": "ig_trouvé",
    "dans_cible": false,
    "source": "modash",
    "date_contact": null,
    "scraped_at": "2026-05-14T19:05:54.047Z"
  },
  {
    "instagram_handle": "@sebastien_walle",
    "twitter_handle": null,
    "nom": "Sebastien Walle",
    "bio": "FITNESS | BOXING | BRAZILIAN JIUJITSU TRAINER | | | FULL CONTACT BLACK BELT 2nd degree 🥊🥊🥊BRAZILIAN JIUJITSU BLACK BELT 1st degree🥋🥋🥋",
    "ville": "Paris",
    "abonnes_instagram": 4400,
    "abonnes_affiche": "4.4k",
    "secteur": "spa",
    "email_contact": null,
    "tarif_estime": "gratuit/produit",
    "statut": "ig_trouvé",
    "dans_cible": false,
    "source": "modash",
    "date_contact": null,
    "scraped_at": "2026-05-14T19:05:54.047Z"
  },
  {
    "instagram_handle": "@yoan_coach_paris",
    "twitter_handle": null,
    "nom": "Personal Trainer 💥 BOXE & FITNESS",
    "bio": "👨🏻‍🎓Coach Diplômé 🔥Boxe anglaise • Muay Thaï • Musculation 📈Cours privés ou Collectifs, tous niveaux 📍Paris et Haut-de-Seine (92) 📩Réservation en MP",
    "ville": "Paris",
    "abonnes_instagram": 3300,
    "abonnes_affiche": "3.3k",
    "secteur": "spa",
    "email_contact": null,
    "tarif_estime": "gratuit/produit",
    "statut": "ig_trouvé",
    "dans_cible": false,
    "source": "modash",
    "date_contact": null,
    "scraped_at": "2026-05-14T19:05:54.047Z"
  },
  {
    "instagram_handle": "@anaisjazmine",
    "twitter_handle": null,
    "nom": "Anaïs Jazmine",
    "bio": "Celebrities Trainer ~ @forbes woman 🇲🇦 Influence | Lifestyle | Pilates Fitness & Longevity expert",
    "ville": "Paris",
    "abonnes_instagram": 115400,
    "abonnes_affiche": "115.4k",
    "secteur": "spa",
    "email_contact": null,
    "tarif_estime": "300-600€",
    "statut": "ig_trouvé",
    "dans_cible": false,
    "source": "modash",
    "date_contact": null,
    "scraped_at": "2026-05-14T19:05:54.047Z"
  },
  {
    "instagram_handle": "@ilonadlh",
    "twitter_handle": null,
    "nom": "Ilona Chable De La Héronnière",
    "bio": "🇫🇷 Ilo 🏃🏻‍♀️Fitness 📍Bandol-Nice 🌊sea 🌍Travel 🌞You are the Sun",
    "ville": "Nice",
    "abonnes_instagram": 97700,
    "abonnes_affiche": "97.7k",
    "secteur": "spa",
    "email_contact": null,
    "tarif_estime": "300-600€",
    "statut": "ig_trouvé",
    "dans_cible": false,
    "source": "modash",
    "date_contact": null,
    "scraped_at": "2026-05-14T19:05:54.047Z"
  },
  {
    "instagram_handle": "@theironquest",
    "twitter_handle": null,
    "nom": "IronQuest",
    "bio": "Le YouTubeur qui te parle de l’Histoire du corps tout en t’aidant à forger le tien ! 💪🏻🏛️🏰 Fitness & Histoire",
    "ville": "Paris",
    "abonnes_instagram": null,
    "abonnes_affiche": null,
    "secteur": "spa",
    "email_contact": null,
    "tarif_estime": "gratuit/produit",
    "statut": "ig_trouvé",
    "dans_cible": null,
    "source": "modash",
    "date_contact": null,
    "scraped_at": "2026-05-14T19:05:54.047Z"
  },
  {
    "instagram_handle": "@emeu12healthyfit",
    "twitter_handle": null,
    "nom": "Emeline Savy",
    "bio": "𝙷𝙴𝙰𝙻𝚃𝙷𝚈 𝙵𝙸𝚃𝙽𝙴𝚂𝚂 𝙱𝙴𝙰𝚄𝚃𝚈 𝙵𝙰𝚂𝙷𝙸𝙾𝙽 🄰🅅🄴🄲 🅃🄰🄶🄰🄳🄰🦜 𝑪𝒐𝒂𝒄𝒉 𝒔𝒑𝒐𝒓𝒕𝒊𝒇 &̷ 𝒏𝒖𝒕𝒓𝒊𝒕𝒊𝒐𝒏 𝒆𝒏 𝒍𝒊𝒈𝒏𝒆 𝑼𝑮𝑪 + 𝑨𝑹𝑷𝑷 𝑪𝒆𝒓𝒕𝒊𝒇𝒊𝒆𝒅 𝑪𝑰𝑭 #noanimal...",
    "ville": "Paris",
    "abonnes_instagram": null,
    "abonnes_affiche": null,
    "secteur": "spa",
    "email_contact": null,
    "tarif_estime": "gratuit/produit",
    "statut": "ig_trouvé",
    "dans_cible": null,
    "source": "modash",
    "date_contact": null,
    "scraped_at": "2026-05-14T19:05:54.047Z"
  },
  {
    "instagram_handle": "@et",
    "twitter_handle": null,
    "nom": "Top 50 influenceuses françaises",
    "bio": "31 mai 2025 · Dans le paysage numérique actuel, l’ influenceuse française s’est taillée une place de choix. Avec la montée en puissance des plateformes comme Instagram et TikTok, ces créatrices de …",
    "ville": "Paris",
    "abonnes_instagram": 9000000,
    "abonnes_affiche": "9.0M",
    "secteur": "spa",
    "email_contact": null,
    "tarif_estime": "300-600€",
    "statut": "ig_trouvé",
    "dans_cible": false,
    "source": "bing",
    "date_contact": null,
    "scraped_at": "2026-05-14T19:05:54.047Z"
  },
  {
    "instagram_handle": "@ne.",
    "twitter_handle": null,
    "nom": "Les 20 meilleures influenceuses françaises en 2026 [ ...",
    "bio": "Découvrez le top 20 des influenceuses françaises en 2026 et voyez qui mène les tendances et impacte la mode, la beauté et le lifestyle en ligne.",
    "ville": "Paris",
    "abonnes_instagram": 9000000,
    "abonnes_affiche": "9.0M",
    "secteur": "spa",
    "email_contact": null,
    "tarif_estime": "300-600€",
    "statut": "ig_trouvé",
    "dans_cible": false,
    "source": "bing",
    "date_contact": null,
    "scraped_at": "2026-05-14T19:05:54.047Z"
  },
  {
    "instagram_handle": "@gram",
    "twitter_handle": null,
    "nom": "10 influenceuses françaises à suivre sur Instagram",
    "bio": "4 juin 2025 · Quels conseils pour débuter sur Instagram en tant qu’influenceuse ? Il est essentiel de choisir une niche fidèle à ses passions, soigner son identité visuelle, créer du contenu de qualité, …",
    "ville": "Paris",
    "abonnes_instagram": 9000000,
    "abonnes_affiche": "9.0M",
    "secteur": "spa",
    "email_contact": null,
    "tarif_estime": "300-600€",
    "statut": "ig_trouvé",
    "dans_cible": false,
    "source": "bing",
    "date_contact": null,
    "scraped_at": "2026-05-14T19:05:54.047Z"
  }
]